Workbook

Sheet CONTROL DE LLAMADAS
A1: Nombre de Encuestador: | C1: JUAN FELIPE RAMIREZ LARRIVA | H1: P1 – Motivo principal | I1: P2 – Calificación | J1: Lógica condicional (IMPORTANTE) | L1: P3 – Competencia | N1: P4 – Reactivación | O1: P5 – Disposición Final
H2: Pregunta: | I2: Pregunta: | J2: Si responde: | L2: Pregunta: | M2: Si responde “Sí” → activar pregunta: | N2: Pregunta:
A3: Fila | B3: Fecha de llamada | C3: Estatus de CONTACT | D3: Plaza | E3: Numero Dv | F3: Nombre Dv | G3: fhUltimoCanje | H3: “En una palabra o frase corta, ¿cuál es la principal razón por la que hoy no estás colocando?” | I3: “Del 1 al 5 donde 5 es muy buena y 1 es mala, ¿cómo calificas tu experiencia con la sucursal?” | J3: 1, 2 o 3 → ir a sección “Área de Mejora” como podriamos mejorar? | K3: 4 o 5 → ir a sección “Fortaleza” | L3: “¿Actualmente trabajas con otra financiera?” | M3: “¿Qué es lo que más te gusta de trabajar con ellos?” | N3: ¿Qué Necesitas para ser exclusiva de CRECE CON VALES? | O3: “Si logramos resolver el punto que nos comentas, ¿te gustaría que te contactemos para revisar tu posible reactivación?”
J4: “¿Qué podríamos mejorar?” | K4: “¿Qué es lo que más valoras del servicio?” | O4: Si | P4: Tal vez | Q4: No
A5: 1 | B5: 46073 | C5: No contestó | D5: {=INDEX(BASE!$C:$C,MATCH($A5,BASE!$A:$A,0))} -> ACAYUCAN | E5: {=INDEX(BASE!E:E,MATCH($A5,BASE!$A:$A,0))} -> 86079 | F5: {=INDEX(BASE!F:F,MATCH($A5,BASE!$A:$A,0))} -> MARIA DE LOS ANGELES MEZA REYES | G5: {=INDEX(BASE!J:J,MATCH($A5,BASE!$A:$A,0))} -> 46052
A6: 2 | B6: 46073 | C6: No contestó | D6: {=INDEX(BASE!$C:$C,MATCH($A6,BASE!$A:$A,0))} -> ACAYUCAN | E6: {=INDEX(BASE!E:E,MATCH($A6,BASE!$A:$A,0))} -> 86166 | F6: {=INDEX(BASE!F:F,MATCH($A6,BASE!$A:$A,0))} -> GABRIELA SANCHEZ GONZALEZ | G6: {=INDEX(BASE!J:J,MATCH($A6,BASE!$A:$A,0))} -> 46051
A7: 3 | B7: 46073 | C7: No contestó | D7: {=INDEX(BASE!$C:$C,MATCH($A7,BASE!$A:$A,0))} -> ACAYUCAN | E7: {=INDEX(BASE!E:E,MATCH($A7,BASE!$A:$A,0))} -> 86052 | F7: {=INDEX(BASE!F:F,MATCH($A7,BASE!$A:$A,0))} -> MARIA DEL CARMEN CRUZ JIMENEZ | G7: {=INDEX(BASE!J:J,MATCH($A7,BASE!$A:$A,0))} -> 46014
A8: 4 | B8: 46073 | C8: No contestó | D8: {=INDEX(BASE!$C:$C,MATCH($A8,BASE!$A:$A,0))} -> ACAYUCAN | E8: {=INDEX(BASE!E:E,MATCH($A8,BASE!$A:$A,0))} -> 109938 | F8: {=INDEX(BASE!F:F,MATCH($A8,BASE!$A:$A,0))} -> PEREZ HERNANDEZ , PETRONILA | G8: {=INDEX(BASE!J:J,MATCH($A8,BASE!$A:$A,0))} -> 46050
A9: 5 | B9: 46073 | C9: Llamada efectiva (contestó) | D9: {=INDEX(BASE!$C:$C,MATCH($A9,BASE!$A:$A,0))} -> ACAYUCAN | E9: {=INDEX(BASE!E:E,MATCH($A9,BASE!$A:$A,0))} -> 86237 | F9: {=INDEX(BASE!F:F,MATCH($A9,BASE!$A:$A,0))} -> HERLINDA LOPEZ NO | G9: {=INDEX(BASE!J:J,MATCH($A9,BASE!$A:$A,0))} -> 46054 | H9: falta de apoyo del promotor, no se le da seguimiento | I9: 5 | K9: facilidades en el servicio de pagos | L9: NO
A10: 6 | B10: 46073 | C10: Reagendar llamada | D10: {=INDEX(BASE!$C:$C,MATCH($A10,BASE!$A:$A,0))} -> ACAYUCAN | E10: {=INDEX(BASE!E:E,MATCH($A10,BASE!$A:$A,0))} -> 116240 | F10: {=INDEX(BASE!F:F,MATCH($A10,BASE!$A:$A,0))} -> NOLASCO BLANCO , ERICK NAHIM | G10: {=INDEX(BASE!J:J,MATCH($A10,BASE!$A:$A,0))} -> 46050
A11: 7 | B11: 46073 | C11: Buzón | D11: {=INDEX(BASE!$C:$C,MATCH($A11,BASE!$A:$A,0))} -> ACAYUCAN | E11: {=INDEX(BASE!E:E,MATCH($A11,BASE!$A:$A,0))} -> 116013 | F11: {=INDEX(BASE!F:F,MATCH($A11,BASE!$A:$A,0))} -> HERNANDEZ MODESTO , ANA BEATRIZ | G11: {=INDEX(BASE!J:J,MATCH($A11,BASE!$A:$A,0))} -> 46028
A12: 8 | B12: 46073 | C12: No contestó | D12: {=INDEX(BASE!$C:$C,MATCH($A12,BASE!$A:$A,0))} -> ACAYUCAN | E12: {=INDEX(BASE!E:E,MATCH($A12,BASE!$A:$A,0))} -> 86024 | F12: {=INDEX(BASE!F:F,MATCH($A12,BASE!$A:$A,0))} -> MARTHA REINA REYES GABINO | G12: {=INDEX(BASE!J:J,MATCH($A12,BASE!$A:$A,0))} -> 45994
A13: 9 | B13: 46073 | C13: No contestó | D13: {=INDEX(BASE!$C:$C,MATCH($A13,BASE!$A:$A,0))} -> ACAYUCAN | E13: {=INDEX(BASE!E:E,MATCH($A13,BASE!$A:$A,0))} -> 86065 | F13: {=INDEX(BASE!F:F,MATCH($A13,BASE!$A:$A,0))} -> NATALI DE MONSERRAT RUIZ VERGARA | G13: {=INDEX(BASE!J:J,MATCH($A13,BASE!$A:$A,0))} -> 45994
A14: 10 | B14: 46073 | C14: Se negó a contestar | D14: {=INDEX(BASE!$C:$C,MATCH($A14,BASE!$A:$A,0))} -> ACAYUCAN | E14: {=INDEX(BASE!E:E,MATCH($A14,BASE!$A:$A,0))} -> 86072 | F14: {=INDEX(BASE!F:F,MATCH($A14,BASE!$A:$A,0))} -> ELIZABETH GUILLEN FERNANDEZ | G14: {=INDEX(BASE!J:J,MATCH($A14,BASE!$A:$A,0))} -> 45962
A15: 11 | B15: 46073 | C15: Se negó a contestar | D15: {=INDEX(BASE!$C:$C,MATCH($A15,BASE!$A:$A,0))} -> ACAYUCAN | E15: {=INDEX(BASE!E:E,MATCH($A15,BASE!$A:$A,0))} -> 86035 | F15: {=INDEX(BASE!F:F,MATCH($A15,BASE!$A:$A,0))} -> MARIA CRISTINA MUÑOZ CARDENAS | G15: {=INDEX(BASE!J:J,MATCH($A15,BASE!$A:$A,0))} -> 46054
A16: 12 | B16: 46073 | C16: No contestó | D16: {=INDEX(BASE!$C:$C,MATCH($A16,BASE!$A:$A,0))} -> ACAYUCAN | E16: {=INDEX(BASE!E:E,MATCH($A16,BASE!$A:$A,0))} -> 109931 | F16: {=INDEX(BASE!F:F,MATCH($A16,BASE!$A:$A,0))} -> AGUIRRE ENRIQUEZ , GUADALUPE | G16: {=INDEX(BASE!J:J,MATCH($A16,BASE!$A:$A,0))} -> 46024
A17: 13 | B17: 46073 | C17: No contestó | D17: {=INDEX(BASE!$C:$C,MATCH($A17,BASE!$A:$A,0))} -> ACAYUCAN | E17: {=INDEX(BASE!E:E,MATCH($A17,BASE!$A:$A,0))} -> 103239 | F17: {=INDEX(BASE!F:F,MATCH($A17,BASE!$A:$A,0))} -> TADEO ANTONIO EVA | G17: {=INDEX(BASE!J:J,MATCH($A17,BASE!$A:$A,0))} -> 46054
A18: 14 | B18: 46073 | C18: Llamada efectiva (contestó) | D18: {=INDEX(BASE!$C:$C,MATCH($A18,BASE!$A:$A,0))} -> ACAYUCAN | E18: {=INDEX(BASE!E:E,MATCH($A18,BASE!$A:$A,0))} -> 86105 | F18: {=INDEX(BASE!F:F,MATCH($A18,BASE!$A:$A,0))} -> ANGELICA TREJO PEREZ | G18: {=INDEX(BASE!J:J,MATCH($A18,BASE!$A:$A,0))} -> 46045 | H18: Comenta que no hay apoyo en cobranza | I18: 2 | J18: estar al tanto y apoyar | L18: SI | M18: Tienen mejor atencion y seguimiento | N18: apoyo | O18: 1
A19: 15 | B19: 46073 | C19: Buzón | D19: {=INDEX(BASE!$C:$C,MATCH($A19,BASE!$A:$A,0))} -> ACAYUCAN | E19: {=INDEX(BASE!E:E,MATCH($A19,BASE!$A:$A,0))} -> 86149 | F19: {=INDEX(BASE!F:F,MATCH($A19,BASE!$A:$A,0))} -> PETRA RAMIREZ USCANGA | G19: {=INDEX(BASE!J:J,MATCH($A19,BASE!$A:$A,0))} -> 46056
A20: 16 | B20: 46073 | C20: Llamada efectiva (contestó) | D20: {=INDEX(BASE!$C:$C,MATCH($A20,BASE!$A:$A,0))} -> ACAYUCAN | E20: {=INDEX(BASE!E:E,MATCH($A20,BASE!$A:$A,0))} -> 86041 | F20: {=INDEX(BASE!F:F,MATCH($A20,BASE!$A:$A,0))} -> ZORAIDA MENDOZA DE JESUS | G20: {=INDEX(BASE!J:J,MATCH($A20,BASE!$A:$A,0))} -> 46056 | H20: falta de confianza, no se quiere arriesgar a que los clientes no le paguen | I20: 2 | J20: no hay motivacion por parte del personal | L20: SI | M20: tienen mejor atencion | N20: piensa en salir de colaborar | O20: 1
A21: 17 | B21: 46073 | C21: No contestó | D21: {=INDEX(BASE!$C:$C,MATCH($A21,BASE!$A:$A,0))} -> ACAYUCAN | E21: {=INDEX(BASE!E:E,MATCH($A21,BASE!$A:$A,0))} -> 86053 | F21: {=INDEX(BASE!F:F,MATCH($A21,BASE!$A:$A,0))} -> NICOLASA HERNANDEZ MARTINEZ | G21: {=INDEX(BASE!J:J,MATCH($A21,BASE!$A:$A,0))} -> 45980
A22: 18 | B22: 46073 | C22: Llamada efectiva (contestó) | D22: {=INDEX(BASE!$C:$C,MATCH($A22,BASE!$A:$A,0))} -> ACAYUCAN | E22: {=INDEX(BASE!E:E,MATCH($A22,BASE!$A:$A,0))} -> 86037 | F22: {=INDEX(BASE!F:F,MATCH($A22,BASE!$A:$A,0))} -> ANA LUISA ZENTENO MARTINEZ | G22: {=INDEX(BASE!J:J,MATCH($A22,BASE!$A:$A,0))} -> 46003 | H22: le teme a que clientes no le paguen | I22: 5 | K22: la atencion y bonificacion | L22: SI | M22: las bonificaciones y el apoyo en cobranza | N22: paciencia | O22: 1
A23: 19 | B23: 46073 | C23: Buzón | D23: {=INDEX(BASE!$C:$C,MATCH($A23,BASE!$A:$A,0))} -> ACAYUCAN | E23: {=INDEX(BASE!E:E,MATCH($A23,BASE!$A:$A,0))} -> 116138 | F23: {=INDEX(BASE!F:F,MATCH($A23,BASE!$A:$A,0))} -> GUILLEN SANTIAGO , ALONDRA | G23: {=INDEX(BASE!J:J,MATCH($A23,BASE!$A:$A,0))} -> 45997
A24: 20 | B24: 46073 | C24: Se negó a contestar | D24: {=INDEX(BASE!$C:$C,MATCH($A24,BASE!$A:$A,0))} -> ACAYUCAN | E24: {=INDEX(BASE!E:E,MATCH($A24,BASE!$A:$A,0))} -> 86083 | F24: {=INDEX(BASE!F:F,MATCH($A24,BASE!$A:$A,0))} -> DORA PEREZ GOMEZ | G24: {=INDEX(BASE!J:J,MATCH($A24,BASE!$A:$A,0))} -> 46017 | H24: no ha buscado clientes | I24: 5 | K24: ya no siguio en la llamada
A25: 21 | B25: 46073 | C25: No contestó | D25: {=INDEX(BASE!$C:$C,MATCH($A25,BASE!$A:$A,0))} -> ACAYUCAN | E25: {=INDEX(BASE!E:E,MATCH($A25,BASE!$A:$A,0))} -> 103924 | F25: {=INDEX(BASE!F:F,MATCH($A25,BASE!$A:$A,0))} -> CORDERO RAMIREZ MARIBEL | G25: {=INDEX(BASE!J:J,MATCH($A25,BASE!$A:$A,0))} -> 45965
A26: 22 | B26: 46073 | C26: No contestó | D26: {=INDEX(BASE!$C:$C,MATCH($A26,BASE!$A:$A,0))} -> ACAYUCAN | E26: {=INDEX(BASE!E:E,MATCH($A26,BASE!$A:$A,0))} -> 107170 | F26: {=INDEX(BASE!F:F,MATCH($A26,BASE!$A:$A,0))} -> ISIDORO CANDIDO , ALEJANDRA | G26: {=INDEX(BASE!J:J,MATCH($A26,BASE!$A:$A,0))} -> 45962
A27: 23 | B27: 46073 | C27: Llamada efectiva (contestó) | D27: {=INDEX(BASE!$C:$C,MATCH($A27,BASE!$A:$A,0))} -> ACAYUCAN | E27: {=INDEX(BASE!E:E,MATCH($A27,BASE!$A:$A,0))} -> 110417 | F27: {=INDEX(BASE!F:F,MATCH($A27,BASE!$A:$A,0))} -> PULIDO LICONA , VERONICA | G27: {=INDEX(BASE!J:J,MATCH($A27,BASE!$A:$A,0))} -> 46003 | H27: vive en una zona donde hay muchos prestanombres | I27: 3 | J27: ayuda en cobranza, no hay apoyo | L27: SI | M27: apoyan con la cobranza | N27: mas atencion por parte de la financiera | Q27: 1
A28: 24 | B28: 46073 | C28: Llamada efectiva (contestó) | D28: {=INDEX(BASE!$C:$C,MATCH($A28,BASE!$A:$A,0))} -> ACAYUCAN | E28: {=INDEX(BASE!E:E,MATCH($A28,BASE!$A:$A,0))} -> 108567 | F28: {=INDEX(BASE!F:F,MATCH($A28,BASE!$A:$A,0))} -> DOMINGUEZ ALFONSO , MARIA ELENA | G28: {=INDEX(BASE!J:J,MATCH($A28,BASE!$A:$A,0))} -> 46054 | H28: no lleva prisa, no se quiere saturar | I28: 5 | K28: se le ha brindado apoyo | L28: SI | M28: se siente comoda | N28: tener una buena selección de clientes | O28: 1
A29: 25 | B29: 46073 | C29: No contestó | D29: {=INDEX(BASE!$C:$C,MATCH($A29,BASE!$A:$A,0))} -> ALTAMIRA | E29: {=INDEX(BASE!E:E,MATCH($A29,BASE!$A:$A,0))} -> 57216 | F29: {=INDEX(BASE!F:F,MATCH($A29,BASE!$A:$A,0))} -> MARIA GUADALUPE AQUINO BANDA | G29: {=INDEX(BASE!J:J,MATCH($A29,BASE!$A:$A,0))} -> 45909
A30: 26 | B30: 46073 | C30: Buzón | D30: {=INDEX(BASE!$C:$C,MATCH($A30,BASE!$A:$A,0))} -> ALTAMIRA | E30: {=INDEX(BASE!E:E,MATCH($A30,BASE!$A:$A,0))} -> 57064 | F30: {=INDEX(BASE!F:F,MATCH($A30,BASE!$A:$A,0))} -> MARIA CONCEPCION LOREDO AVALOS | G30: {=INDEX(BASE!J:J,MATCH($A30,BASE!$A:$A,0))} -> 45981
A31: 27 | B31: 46073 | C31: Buzón | D31: {=INDEX(BASE!$C:$C,MATCH($A31,BASE!$A:$A,0))} -> ALTAMIRA | E31: {=INDEX(BASE!E:E,MATCH($A31,BASE!$A:$A,0))} -> 57306 | F31: {=INDEX(BASE!F:F,MATCH($A31,BASE!$A:$A,0))} -> BERENICE SEGURA DEL ANGEL | G31: {=INDEX(BASE!J:J,MATCH($A31,BASE!$A:$A,0))} -> 46022
A32: 28 | B32: 46073 | C32: Buzón | D32: {=INDEX(BASE!$C:$C,MATCH($A32,BASE!$A:$A,0))} -> ALTAMIRA | E32: {=INDEX(BASE!E:E,MATCH($A32,BASE!$A:$A,0))} -> 57403 | F32: {=INDEX(BASE!F:F,MATCH($A32,BASE!$A:$A,0))} -> JOSE LUIS GUZMAN MADRIGALES | G32: {=INDEX(BASE!J:J,MATCH($A32,BASE!$A:$A,0))} -> 46021
A33: 29 | B33: 46073 | C33: Buzón | D33: {=INDEX(BASE!$C:$C,MATCH($A33,BASE!$A:$A,0))} -> ALTAMIRA | E33: {=INDEX(BASE!E:E,MATCH($A33,BASE!$A:$A,0))} -> 57363 | F33: {=INDEX(BASE!F:F,MATCH($A33,BASE!$A:$A,0))} -> GUADALUPE FLORES GUZMAN | G33: {=INDEX(BASE!J:J,MATCH($A33,BASE!$A:$A,0))} -> 45938
A34: 30 | B34: 46073 | C34: No contestó | D34: {=INDEX(BASE!$C:$C,MATCH($A34,BASE!$A:$A,0))} -> ALTAMIRA | E34: {=INDEX(BASE!E:E,MATCH($A34,BASE!$A:$A,0))} -> 104106 | F34: {=INDEX(BASE!F:F,MATCH($A34,BASE!$A:$A,0))} -> GERONIMO FRANCO DORA ALICIA | G34: {=INDEX(BASE!J:J,MATCH($A34,BASE!$A:$A,0))} -> 46058
A35: 31 | B35: 46073 | C35: No contestó | D35: {=INDEX(BASE!$C:$C,MATCH($A35,BASE!$A:$A,0))} -> ALTAMIRA | E35: {=INDEX(BASE!E:E,MATCH($A35,BASE!$A:$A,0))} -> 57088 | F35: {=INDEX(BASE!F:F,MATCH($A35,BASE!$A:$A,0))} -> MARIA VICTORIA GARCIA SOLIS | G35: {=INDEX(BASE!J:J,MATCH($A35,BASE!$A:$A,0))} -> 45967
A36: 32 | B36: 46073 | C36: Llamada efectiva (contestó) | D36: {=INDEX(BASE!$C:$C,MATCH($A36,BASE!$A:$A,0))} -> ALTAMIRA | E36: {=INDEX(BASE!E:E,MATCH($A36,BASE!$A:$A,0))} -> 57290 | F36: {=INDEX(BASE!F:F,MATCH($A36,BASE!$A:$A,0))} -> NORMA ELIZABETH SALAS MAR | G36: {=INDEX(BASE!J:J,MATCH($A36,BASE!$A:$A,0))} -> 46059 | H36: Ya tiene una lista de clientes fieles y no se quiere arriesgar a que no le paguen | I36: 5 | K36: que no se ha sentido presionada | L36: SI | M36: tiene mas comodidades | N36: perder el miedo a que no le paguen | O36: 1
A37: 33 | B37: 46073 | C37: Llamada efectiva (contestó) | D37: {=INDEX(BASE!$C:$C,MATCH($A37,BASE!$A:$A,0))} -> ALTAMIRA | E37: {=INDEX(BASE!E:E,MATCH($A37,BASE!$A:$A,0))} -> 57243 | F37: {=INDEX(BASE!F:F,MATCH($A37,BASE!$A:$A,0))} -> CLARABELLA HERNANDEZ ALONSO | G37: {=INDEX(BASE!J:J,MATCH($A37,BASE!$A:$A,0))} -> 45980 | H37: le da prioridad a los clientes cumplidos | I37: 5 | K37: se le ha dado el apoyo | L37: SI | M37: Las facilidades | N37: buscar clientes responsables | O37: 1
A38: 34 | B38: 46073 | C38: No contestó | D38: {=INDEX(BASE!$C:$C,MATCH($A38,BASE!$A:$A,0))} -> ALTAMIRA | E38: {=INDEX(BASE!E:E,MATCH($A38,BASE!$A:$A,0))} -> 57212 | F38: {=INDEX(BASE!F:F,MATCH($A38,BASE!$A:$A,0))} -> EDUVIGES RODRIGUEZ PONCE | G38: {=INDEX(BASE!J:J,MATCH($A38,BASE!$A:$A,0))} -> 46021
A39: 35 | B39: 46073 | C39: No contestó | D39: {=INDEX(BASE!$C:$C,MATCH($A39,BASE!$A:$A,0))} -> ALTAMIRA | E39: {=INDEX(BASE!E:E,MATCH($A39,BASE!$A:$A,0))} -> 106746 | F39: {=INDEX(BASE!F:F,MATCH($A39,BASE!$A:$A,0))} -> YAÑEZ MARTINEZ , MARIA LOURDES | G39: {=INDEX(BASE!J:J,MATCH($A39,BASE!$A:$A,0))} -> 45925
A40: 36 | B40: 46073 | C40: Buzón | D40: {=INDEX(BASE!$C:$C,MATCH($A40,BASE!$A:$A,0))} -> ALTAMIRA | E40: {=INDEX(BASE!E:E,MATCH($A40,BASE!$A:$A,0))} -> 110263 | F40: {=INDEX(BASE!F:F,MATCH($A40,BASE!$A:$A,0))} -> CAMPOZANO FLORES , ELENA | G40: {=INDEX(BASE!J:J,MATCH($A40,BASE!$A:$A,0))} -> 46058
A41: 37 | B41: 46073 | C41: Llamada efectiva (contestó) | D41: {=INDEX(BASE!$C:$C,MATCH($A41,BASE!$A:$A,0))} -> ALTAMIRA | E41: {=INDEX(BASE!E:E,MATCH($A41,BASE!$A:$A,0))} -> 57299 | F41: {=INDEX(BASE!F:F,MATCH($A41,BASE!$A:$A,0))} -> VICTORIA LARA ZARAGOZA | G41: {=INDEX(BASE!J:J,MATCH($A41,BASE!$A:$A,0))} -> 46053 | H41: no ha tenido clientes | I41: 3 | J41: no hay buenos prestamos personales | L41: si | M41: le facilitan prestamos personales | N41: que le presten dinero | O41: 1
A42: 38 | B42: 46073 | C42: Llamada efectiva (contestó) | D42: {=INDEX(BASE!$C:$C,MATCH($A42,BASE!$A:$A,0))} -> ALTAMIRA | E42: {=INDEX(BASE!E:E,MATCH($A42,BASE!$A:$A,0))} -> 113504 | F42: {=INDEX(BASE!F:F,MATCH($A42,BASE!$A:$A,0))} -> SOBREVILLA PEREZ , AURORA | G42: {=INDEX(BASE!J:J,MATCH($A42,BASE!$A:$A,0))} -> 46007 | H42: no le da vales a cualquier persona, no quiere problemas | I42: 5 | L42: si | M42: le dan premios y regalos | N42: no le interesa | P42: 1
A43: 39 | B43: 46073 | C43: Llamada efectiva (contestó) | D43: {=INDEX(BASE!$C:$C,MATCH($A43,BASE!$A:$A,0))} -> ALTAMIRA | E43: {=INDEX(BASE!E:E,MATCH($A43,BASE!$A:$A,0))} -> 57345 | F43: {=INDEX(BASE!F:F,MATCH($A43,BASE!$A:$A,0))} -> ANA MARISELA SILVA HERNANDEZ | G43: {=INDEX(BASE!J:J,MATCH($A43,BASE!$A:$A,0))} -> 46024 | H43: tiene cuidado y no da vales a cualquiera ya tiene sus clientes | I43: 2 | J43: capacitar bien a los coordinadores | L43: si | M43: el buen trato | N43: no le interesa | P43: 1
A44: 40 | B44: 46073 | C44: No contestó | D44: {=INDEX(BASE!$C:$C,MATCH($A44,BASE!$A:$A,0))} -> ALTAMIRA | E44: {=INDEX(BASE!E:E,MATCH($A44,BASE!$A:$A,0))} -> 115703 | F44: {=INDEX(BASE!F:F,MATCH($A44,BASE!$A:$A,0))} -> ANDONEY SANTIAGO , TERESA | G44: {=INDEX(BASE!J:J,MATCH($A44,BASE!$A:$A,0))} -> 46007
A45: 41 | B45: 46073 | C45: No contestó | D45: {=INDEX(BASE!$C:$C,MATCH($A45,BASE!$A:$A,0))} -> ALTAMIRA | E45: {=INDEX(BASE!E:E,MATCH($A45,BASE!$A:$A,0))} -> 57225 | F45: {=INDEX(BASE!F:F,MATCH($A45,BASE!$A:$A,0))} -> MARTHA PATRICIA LOZANO RIVAS | G45: {=INDEX(BASE!J:J,MATCH($A45,BASE!$A:$A,0))} -> 45981
A46: 42 | B46: 46073 | C46: Llamada efectiva (contestó) | D46: {=INDEX(BASE!$C:$C,MATCH($A46,BASE!$A:$A,0))} -> ALTAMIRA | E46: {=INDEX(BASE!E:E,MATCH($A46,BASE!$A:$A,0))} -> 57163 | F46: {=INDEX(BASE!F:F,MATCH($A46,BASE!$A:$A,0))} -> VILLALOBOS ARIAS , AMANDA | G46: {=INDEX(BASE!J:J,MATCH($A46,BASE!$A:$A,0))} -> 46052 | H46: tiene clientes selecionados | I46: 5 | K46: le atienden rapido | L46: si | M46: le dan un buen servicio | N46: tener mas porcentaje de comisiones | O46: 1
A47: 43 | B47: 46073 | C47: Buzón | D47: {=INDEX(BASE!$C:$C,MATCH($A47,BASE!$A:$A,0))} -> ALTAMIRA | E47: {=INDEX(BASE!E:E,MATCH($A47,BASE!$A:$A,0))} -> 57371 | F47: {=INDEX(BASE!F:F,MATCH($A47,BASE!$A:$A,0))} -> REBOLLAR TORRES , NANCY MARGARITA | G47: {=INDEX(BASE!J:J,MATCH($A47,BASE!$A:$A,0))} -> 46058
A48: 44 | B48: 46073 | C48: Buzón | D48: {=INDEX(BASE!$C:$C,MATCH($A48,BASE!$A:$A,0))} -> ALTAMIRA | E48: {=INDEX(BASE!E:E,MATCH($A48,BASE!$A:$A,0))} -> 57276 | F48: {=INDEX(BASE!F:F,MATCH($A48,BASE!$A:$A,0))} -> MARTHA PECERO HERNANDEZ | G48: {=INDEX(BASE!J:J,MATCH($A48,BASE!$A:$A,0))} -> 46009
A49: 45 | B49: 46073 | C49: Llamada efectiva (contestó) | D49: {=INDEX(BASE!$C:$C,MATCH($A49,BASE!$A:$A,0))} -> ALTAMIRA | E49: {=INDEX(BASE!E:E,MATCH($A49,BASE!$A:$A,0))} -> 107732 | F49: {=INDEX(BASE!F:F,MATCH($A49,BASE!$A:$A,0))} -> VIGIL IBARRA , EUNICE | G49: {=INDEX(BASE!J:J,MATCH($A49,BASE!$A:$A,0))} -> 46057 | H49: no le han pedido mas vales sus clientes, no quiere dar mas a nuevos clientes | I49: 5 | K49: los tramites son rapidos | L49: si | M49: tiene ahorro cada año | N49: no le interesa ser exclusiva | O49: 1
A50: 46 | B50: 46073 | C50: Buzón | D50: {=INDEX(BASE!$C:$C,MATCH($A50,BASE!$A:$A,0))} -> BAHIA | E50: {=INDEX(BASE!E:E,MATCH($A50,BASE!$A:$A,0))} -> 105647 | F50: {=INDEX(BASE!F:F,MATCH($A50,BASE!$A:$A,0))} -> TAPIA MARIN KARLA CAROLINA | G50: {=INDEX(BASE!J:J,MATCH($A50,BASE!$A:$A,0))} -> 46056
A51: 47 | B51: 46073 | C51: No contestó | D51: {=INDEX(BASE!$C:$C,MATCH($A51,BASE!$A:$A,0))} -> BAHIA | E51: {=INDEX(BASE!E:E,MATCH($A51,BASE!$A:$A,0))} -> 32148 | F51: {=INDEX(BASE!F:F,MATCH($A51,BASE!$A:$A,0))} -> GRACIELA VALENZUELA RODRIGUEZ | G51: {=INDEX(BASE!J:J,MATCH($A51,BASE!$A:$A,0))} -> 46057
A52: 48 | B52: 46073 | C52: Llamada efectiva (contestó) | D52: {=INDEX(BASE!$C:$C,MATCH($A52,BASE!$A:$A,0))} -> BAHIA | E52: {=INDEX(BASE!E:E,MATCH($A52,BASE!$A:$A,0))} -> 108163 | F52: {=INDEX(BASE!F:F,MATCH($A52,BASE!$A:$A,0))} -> IBARRA CARO , NADIA LIZBETH | G52: {=INDEX(BASE!J:J,MATCH($A52,BASE!$A:$A,0))} -> 45988 | H52: ha tenido retardos para abonar por clientes que no le pagan | I52: 3 | J52: en apoyar en cobranza | L52: si | M52: mas facilidades | N52: no le interesa ser exclusiva | P52: 1
A53: 49 | B53: 46073 | C53: Buzón | D53: {=INDEX(BASE!$C:$C,MATCH($A53,BASE!$A:$A,0))} -> BAHIA | E53: {=INDEX(BASE!E:E,MATCH($A53,BASE!$A:$A,0))} -> 112573 | F53: {=INDEX(BASE!F:F,MATCH($A53,BASE!$A:$A,0))} -> RODRIGUEZ GUZMAN , ANAHI GUADALUPE | G53: {=INDEX(BASE!J:J,MATCH($A53,BASE!$A:$A,0))} -> 45911
A54: 50 | B54: 46073 | C54: Buzón | D54: {=INDEX(BASE!$C:$C,MATCH($A54,BASE!$A:$A,0))} -> BAHIA | E54: {=INDEX(BASE!E:E,MATCH($A54,BASE!$A:$A,0))} -> 106982 | F54: {=INDEX(BASE!F:F,MATCH($A54,BASE!$A:$A,0))} -> RAMIREZ HERNANDEZ MA. ESTHER | G54: {=INDEX(BASE!J:J,MATCH($A54,BASE!$A:$A,0))} -> 45944
A55: 51 | B55: 46073 | C55: Buzón | D55: {=INDEX(BASE!$C:$C,MATCH($A55,BASE!$A:$A,0))} -> BAHIA | E55: {=INDEX(BASE!E:E,MATCH($A55,BASE!$A:$A,0))} -> 104785 | F55: {=INDEX(BASE!F:F,MATCH($A55,BASE!$A:$A,0))} -> GOMEZ GARCIA TOMAS | G55: {=INDEX(BASE!J:J,MATCH($A55,BASE!$A:$A,0))} -> 46024
A56: 52 | B56: 46073 | C56: Buzón | D56: {=INDEX(BASE!$C:$C,MATCH($A56,BASE!$A:$A,0))} -> BAHIA | E56: {=INDEX(BASE!E:E,MATCH($A56,BASE!$A:$A,0))} -> 106099 | F56: {=INDEX(BASE!F:F,MATCH($A56,BASE!$A:$A,0))} -> ESPARZA ALVAREZ DAIRA LIZETTE | G56: {=INDEX(BASE!J:J,MATCH($A56,BASE!$A:$A,0))} -> 45997
A57: 53 | B57: 46073 | C57: No contestó | D57: {=INDEX(BASE!$C:$C,MATCH($A57,BASE!$A:$A,0))} -> BAHIA | E57: {=INDEX(BASE!E:E,MATCH($A57,BASE!$A:$A,0))} -> 113002 | F57: {=INDEX(BASE!F:F,MATCH($A57,BASE!$A:$A,0))} -> CORTEZ MENDOZA , ALEXANDRA | G57: {=INDEX(BASE!J:J,MATCH($A57,BASE!$A:$A,0))} -> 45943
A58: 54 | B58: 46073 | C58: No contestó | D58: {=INDEX(BASE!$C:$C,MATCH($A58,BASE!$A:$A,0))} -> BAHIA | E58: {=INDEX(BASE!E:E,MATCH($A58,BASE!$A:$A,0))} -> 105186 | F58: {=INDEX(BASE!F:F,MATCH($A58,BASE!$A:$A,0))} -> BELLO SANTIAGO HORTENCIA | G58: {=INDEX(BASE!J:J,MATCH($A58,BASE!$A:$A,0))} -> 45945
A59: 55 | B59: 46073 | C59: No contestó | D59: {=INDEX(BASE!$C:$C,MATCH($A59,BASE!$A:$A,0))} -> BAHIA | E59: {=INDEX(BASE!E:E,MATCH($A59,BASE!$A:$A,0))} -> 115750 | F59: {=INDEX(BASE!F:F,MATCH($A59,BASE!$A:$A,0))} -> CONTRERAS CRUZ , LUIS ARMANDO | G59: {=INDEX(BASE!J:J,MATCH($A59,BASE!$A:$A,0))} -> 46009
A60: 56 | B60: 46073 | C60: No contestó | D60: {=INDEX(BASE!$C:$C,MATCH($A60,BASE!$A:$A,0))} -> BAHIA | E60: {=INDEX(BASE!E:E,MATCH($A60,BASE!$A:$A,0))} -> 116863 | F60: {=INDEX(BASE!F:F,MATCH($A60,BASE!$A:$A,0))} -> TAGLE VALENTE , DAMARIS YUNUEN | G60: {=INDEX(BASE!J:J,MATCH($A60,BASE!$A:$A,0))} -> 46049
A61: 57 | B61: 46073 | C61: Buzón | D61: {=INDEX(BASE!$C:$C,MATCH($A61,BASE!$A:$A,0))} -> BAHIA | E61: {=INDEX(BASE!E:E,MATCH($A61,BASE!$A:$A,0))} -> 105401 | F61: {=INDEX(BASE!F:F,MATCH($A61,BASE!$A:$A,0))} -> ARENAS SANDOVAL ANALLELI GUADALUPE | G61: {=INDEX(BASE!J:J,MATCH($A61,BASE!$A:$A,0))} -> 46009
A62: 58 | B62: 46073 | C62: No contestó | D62: {=INDEX(BASE!$C:$C,MATCH($A62,BASE!$A:$A,0))} -> BAHIA | E62: {=INDEX(BASE!E:E,MATCH($A62,BASE!$A:$A,0))} -> 112695 | F62: {=INDEX(BASE!F:F,MATCH($A62,BASE!$A:$A,0))} -> RODRIGUEZ DIAZ , NORMA ALICIA | G62: {=INDEX(BASE!J:J,MATCH($A62,BASE!$A:$A,0))} -> 46028
A63: 59 | B63: 46073 | C63: No contestó | D63: {=INDEX(BASE!$C:$C,MATCH($A63,BASE!$A:$A,0))} -> BAHIA | E63: {=INDEX(BASE!E:E,MATCH($A63,BASE!$A:$A,0))} -> 110356 | F63: {=INDEX(BASE!F:F,MATCH($A63,BASE!$A:$A,0))} -> FRANCO CRUZ , NORMA YADIRA | G63: {=INDEX(BASE!J:J,MATCH($A63,BASE!$A:$A,0))} -> 46059
A64: 60 | B64: 46073 | C64: Buzón | D64: {=INDEX(BASE!$C:$C,MATCH($A64,BASE!$A:$A,0))} -> BAHIA | E64: {=INDEX(BASE!E:E,MATCH($A64,BASE!$A:$A,0))} -> 105822 | F64: {=INDEX(BASE!F:F,MATCH($A64,BASE!$A:$A,0))} -> MARQUEZ JACOBO MARITZA | G64: {=INDEX(BASE!J:J,MATCH($A64,BASE!$A:$A,0))} -> 46059
... A66: 62 | B66: 46073 | C66: Buzón | D66: {=INDEX(BASE!$C:$C,MATCH($A66,BASE!$A:$A,0))} -> CARDENAS | E66: {=INDEX(BASE!E:E,MATCH($A66,BASE!$A:$A,0))} -> 103594 | F66: {=INDEX(BASE!F:F,MATCH($A66,BASE!$A:$A,0))} -> PEREZ GONZALEZ BLANCA ESTELA | G66: {=INDEX(BASE!J:J,MATCH($A66,BASE!$A:$A,0))} -> 45881
A67: 63 | B67: 46073 | C67: Se negó a contestar | D67: {=INDEX(BASE!$C:$C,MATCH($A67,BASE!$A:$A,0))} -> CARDENAS | E67: {=INDEX(BASE!E:E,MATCH($A67,BASE!$A:$A,0))} -> 77003 | F67: {=INDEX(BASE!F:F,MATCH($A67,BASE!$A:$A,0))} -> ENEIDA PEREZ GARCIA | G67: {=INDEX(BASE!J:J,MATCH($A67,BASE!$A:$A,0))} -> 45991 | H67: ya no le interesa formar parte de la financiera
A68: 64 | B68: 46073 | C68: Se negó a contestar | D68: {=INDEX(BASE!$C:$C,MATCH($A68,BASE!$A:$A,0))} -> CARDENAS | E68: {=INDEX(BASE!E:E,MATCH($A68,BASE!$A:$A,0))} -> 77063 | F68: {=INDEX(BASE!F:F,MATCH($A68,BASE!$A:$A,0))} -> GUADALUPE RIVERA SANCHEZ | G68: {=INDEX(BASE!J:J,MATCH($A68,BASE!$A:$A,0))} -> 45964
A69: 65 | B69: 46073 | C69: No contestó | D69: {=INDEX(BASE!$C:$C,MATCH($A69,BASE!$A:$A,0))} -> CARDENAS | E69: {=INDEX(BASE!E:E,MATCH($A69,BASE!$A:$A,0))} -> 77066 | F69: {=INDEX(BASE!F:F,MATCH($A69,BASE!$A:$A,0))} -> ADRIANA GAMAS QUIROGA | G69: {=INDEX(BASE!J:J,MATCH($A69,BASE!$A:$A,0))} -> 46055
A70: 66 | B70: 46073 | C70: No contestó | D70: {=INDEX(BASE!$C:$C,MATCH($A70,BASE!$A:$A,0))} -> CARDENAS | E70: {=INDEX(BASE!E:E,MATCH($A70,BASE!$A:$A,0))} -> 77176 | F70: {=INDEX(BASE!F:F,MATCH($A70,BASE!$A:$A,0))} -> GLORIA DEL JESUS JIMENEZ HIDALGO | G70: {=INDEX(BASE!J:J,MATCH($A70,BASE!$A:$A,0))} -> 46030
A71: 67 | B71: 46073 | C71: Llamada efectiva (contestó) | D71: {=INDEX(BASE!$C:$C,MATCH($A71,BASE!$A:$A,0))} -> CARDENAS | E71: {=INDEX(BASE!E:E,MATCH($A71,BASE!$A:$A,0))} -> 105314 | F71: {=INDEX(BASE!F:F,MATCH($A71,BASE!$A:$A,0))} -> FLORES GOMEZ CINDY RUBI | G71: {=INDEX(BASE!J:J,MATCH($A71,BASE!$A:$A,0))} -> 46054 | H71: falta de renovacion de clientes, no le interesa crecer su cartera | I71: 3 | J71: falta de motivacion, falta de eventos | L71: no | O71: 1
A72: 68 | B72: 46073 | C72: Llamada efectiva (contestó) | D72: {=INDEX(BASE!$C:$C,MATCH($A72,BASE!$A:$A,0))} -> CARDENAS | E72: {=INDEX(BASE!E:E,MATCH($A72,BASE!$A:$A,0))} -> 77020 | F72: {=INDEX(BASE!F:F,MATCH($A72,BASE!$A:$A,0))} -> DANELLI LOPEZ MARTINEZ | G72: {=INDEX(BASE!J:J,MATCH($A72,BASE!$A:$A,0))} -> 46049 | H72: esta pasando por problemas de salud | I72: 3 | J72: apoyo en cobranza | L72: si | M72: hay mas beneficios y premios | N72: que la fiananciera baje sus intereses | O72: 1
A73: 69 | B73: 46073 | C73: No contestó | D73: {=INDEX(BASE!$C:$C,MATCH($A73,BASE!$A:$A,0))} -> CARDENAS | E73: {=INDEX(BASE!E:E,MATCH($A73,BASE!$A:$A,0))} -> 108220 | F73: {=INDEX(BASE!F:F,MATCH($A73,BASE!$A:$A,0))} -> OLAN GARCIA , YOSHIO | G73: {=INDEX(BASE!J:J,MATCH($A73,BASE!$A:$A,0))} -> 46051
A74: 70 | B74: 46073 | C74: Llamada efectiva (contestó) | D74: {=INDEX(BASE!$C:$C,MATCH($A74,BASE!$A:$A,0))} -> CARDENAS | E74: {=INDEX(BASE!E:E,MATCH($A74,BASE!$A:$A,0))} -> 105585 | F74: {=INDEX(BASE!F:F,MATCH($A74,BASE!$A:$A,0))} -> DE LA CRUZ ZAMORA LIDIA DEL CARMEN | G74: {=INDEX(BASE!J:J,MATCH($A74,BASE!$A:$A,0))} -> 45916 | H74: ya no quiere seguir por problemas de salud | I74: 4 | K74: la buena atencion
A75: 71 | B75: 46073 | C75: No contestó | D75: {=INDEX(BASE!$C:$C,MATCH($A75,BASE!$A:$A,0))} -> CARDENAS | E75: {=INDEX(BASE!E:E,MATCH($A75,BASE!$A:$A,0))} -> 77202 | F75: {=INDEX(BASE!F:F,MATCH($A75,BASE!$A:$A,0))} -> ESTRELLA OLAN ALEGRIA | G75: {=INDEX(BASE!J:J,MATCH($A75,BASE!$A:$A,0))} -> 45936
A76: 72 | B76: 46073 | C76: Buzón | D76: {=INDEX(BASE!$C:$C,MATCH($A76,BASE!$A:$A,0))} -> CARDENAS | E76: {=INDEX(BASE!E:E,MATCH($A76,BASE!$A:$A,0))} -> 106979 | F76: {=INDEX(BASE!F:F,MATCH($A76,BASE!$A:$A,0))} -> DE LA CRUZ GOMEZ , DOLORES | G76: {=INDEX(BASE!J:J,MATCH($A76,BASE!$A:$A,0))} -> 46054
A77: 73 | B77: 46073 | C77: Llamada efectiva (contestó) | D77: {=INDEX(BASE!$C:$C,MATCH($A77,BASE!$A:$A,0))} -> CARDENAS | E77: {=INDEX(BASE!E:E,MATCH($A77,BASE!$A:$A,0))} -> 117047 | F77: {=INDEX(BASE!F:F,MATCH($A77,BASE!$A:$A,0))} -> CALIX GOMEZ , YENI | G77: {=INDEX(BASE!J:J,MATCH($A77,BASE!$A:$A,0))} -> 46055 | H77: no se quiere arriesgar con nuevos clientes | I77: 5 | K77: la amabilidad y la atencion | L77: si | M77: tienen mejor facilidades | N77: tener mejor credito en la financiera | O77: 1
A78: 74 | B78: 46073 | C78: Se negó a contestar | D78: {=INDEX(BASE!$C:$C,MATCH($A78,BASE!$A:$A,0))} -> CARDENAS | E78: {=INDEX(BASE!E:E,MATCH($A78,BASE!$A:$A,0))} -> 109597 | F78: {=INDEX(BASE!F:F,MATCH($A78,BASE!$A:$A,0))} -> FUENTES HERNANDEZ , CAROLINA | G78: {=INDEX(BASE!J:J,MATCH($A78,BASE!$A:$A,0))} -> 45881 | H78: se molesto y dice que no brindan el apoyo necesario
A79: 75 | B79: 46073 | C79: No contestó | D79: {=INDEX(BASE!$C:$C,MATCH($A79,BASE!$A:$A,0))} -> CARDENAS | E79: {=INDEX(BASE!E:E,MATCH($A79,BASE!$A:$A,0))} -> 109448 | F79: {=INDEX(BASE!F:F,MATCH($A79,BASE!$A:$A,0))} -> DE LA CRUZ SAUZ , CARLOS | G79: {=INDEX(BASE!J:J,MATCH($A79,BASE!$A:$A,0))} -> 46058
A80: 76 | B80: 46073 | C80: Buzón | D80: {=INDEX(BASE!$C:$C,MATCH($A80,BASE!$A:$A,0))} -> CARDENAS | E80: {=INDEX(BASE!E:E,MATCH($A80,BASE!$A:$A,0))} -> 103951 | F80: {=INDEX(BASE!F:F,MATCH($A80,BASE!$A:$A,0))} -> REYES RODRIGUEZ CLARA AURORA | G80: {=INDEX(BASE!J:J,MATCH($A80,BASE!$A:$A,0))} -> 46053
A81: 77 | B81: 46073 | C81: No contestó | D81: {=INDEX(BASE!$C:$C,MATCH($A81,BASE!$A:$A,0))} -> CARDENAS | E81: {=INDEX(BASE!E:E,MATCH($A81,BASE!$A:$A,0))} -> 108635 | F81: {=INDEX(BASE!F:F,MATCH($A81,BASE!$A:$A,0))} -> DOMINGUEZ HERNANDEZ , GUADALUPE | G81: {=INDEX(BASE!J:J,MATCH($A81,BASE!$A:$A,0))} -> 46052
A82: 78 | B82: 46073 | C82: Buzón | D82: {=INDEX(BASE!$C:$C,MATCH($A82,BASE!$A:$A,0))} -> CARDENAS | E82: {=INDEX(BASE!E:E,MATCH($A82,BASE!$A:$A,0))} -> 116912 | F82: {=INDEX(BASE!F:F,MATCH($A82,BASE!$A:$A,0))} -> BLANCO SOSA , ANAHI | G82: {=INDEX(BASE!J:J,MATCH($A82,BASE!$A:$A,0))} -> 46049
A83: 79 | B83: 46073 | C83: Llamada efectiva (contestó) | D83: {=INDEX(BASE!$C:$C,MATCH($A83,BASE!$A:$A,0))} -> CARDENAS | E83: {=INDEX(BASE!E:E,MATCH($A83,BASE!$A:$A,0))} -> 116732 | F83: {=INDEX(BASE!F:F,MATCH($A83,BASE!$A:$A,0))} -> ESPITIA SANTOS , SANDY | G83: {=INDEX(BASE!J:J,MATCH($A83,BASE!$A:$A,0))} -> 46014 | H83: esta esperando jalar a sus clientes de otra financiera a crece | I83: 4 | K83: el interes | L83: si | M83: hay mas facilidades en general | N83: es su proposito y su meta | O83: 1
A84: 80 | B84: 46073 | C84: Buzón | D84: {=INDEX(BASE!$C:$C,MATCH($A84,BASE!$A:$A,0))} -> CARDENAS | E84: {=INDEX(BASE!E:E,MATCH($A84,BASE!$A:$A,0))} -> 106130 | F84: {=INDEX(BASE!F:F,MATCH($A84,BASE!$A:$A,0))} -> PINEDA PALMA FABIOLA | G84: {=INDEX(BASE!J:J,MATCH($A84,BASE!$A:$A,0))} -> 45979
A85: 81 | B85: 46073 | C85: Buzón | D85: {=INDEX(BASE!$C:$C,MATCH($A85,BASE!$A:$A,0))} -> CARDENAS | E85: {=INDEX(BASE!E:E,MATCH($A85,BASE!$A:$A,0))} -> 109300 | F85: {=INDEX(BASE!F:F,MATCH($A85,BASE!$A:$A,0))} -> PINEDA ALEJANDRO , VIVIANA | G85: {=INDEX(BASE!J:J,MATCH($A85,BASE!$A:$A,0))} -> 46014
A86: 82 | B86: 46073 | C86: Buzón | D86: {=INDEX(BASE!$C:$C,MATCH($A86,BASE!$A:$A,0))} -> CARDENAS | E86: {=INDEX(BASE!E:E,MATCH($A86,BASE!$A:$A,0))} -> 77185 | F86: {=INDEX(BASE!F:F,MATCH($A86,BASE!$A:$A,0))} -> MARIA CRISTINA QUETCHUM JIMENEZ | G86: {=INDEX(BASE!J:J,MATCH($A86,BASE!$A:$A,0))} -> 46027
A87: 83 | B87: 46073 | C87: Se negó a contestar | D87: {=INDEX(BASE!$C:$C,MATCH($A87,BASE!$A:$A,0))} -> CARDENAS | E87: {=INDEX(BASE!E:E,MATCH($A87,BASE!$A:$A,0))} -> 112110 | F87: {=INDEX(BASE!F:F,MATCH($A87,BASE!$A:$A,0))} -> ESCALANTE LOPEZ , NIDIA MARIA | G87: {=INDEX(BASE!J:J,MATCH($A87,BASE!$A:$A,0))} -> 46022 | H87: se encuentra hospitalizada
A88: 84 | B88: 46073 | C88: No contestó | D88: {=INDEX(BASE!$C:$C,MATCH($A88,BASE!$A:$A,0))} -> CARDENAS | E88: {=INDEX(BASE!E:E,MATCH($A88,BASE!$A:$A,0))} -> 116399 | F88: {=INDEX(BASE!F:F,MATCH($A88,BASE!$A:$A,0))} -> REYES DE LA CRUZ , ISABEL | G88: {=INDEX(BASE!J:J,MATCH($A88,BASE!$A:$A,0))} -> 46011
A89: 85 | B89: 46073 | C89: No contestó | D89: {=INDEX(BASE!$C:$C,MATCH($A89,BASE!$A:$A,0))} -> CARDENAS | E89: {=INDEX(BASE!E:E,MATCH($A89,BASE!$A:$A,0))} -> 113201 | F89: {=INDEX(BASE!F:F,MATCH($A89,BASE!$A:$A,0))} -> JIMENEZ GOMEZ , BELEM | G89: {=INDEX(BASE!J:J,MATCH($A89,BASE!$A:$A,0))} -> 45875
A90: 86 | B90: 46073 | C90: Número cambiado | D90: {=INDEX(BASE!$C:$C,MATCH($A90,BASE!$A:$A,0))} -> CARDENAS | E90: {=INDEX(BASE!E:E,MATCH($A90,BASE!$A:$A,0))} -> 106215 | F90: {=INDEX(BASE!F:F,MATCH($A90,BASE!$A:$A,0))} -> CASTAÑEDA RAMOS LIZBETH | G90: {=INDEX(BASE!J:J,MATCH($A90,BASE!$A:$A,0))} -> 46027 | H90: no aparece el numero de telefono
A91: 87 | B91: 46073 | C91: Buzón | D91: {=INDEX(BASE!$C:$C,MATCH($A91,BASE!$A:$A,0))} -> CARDENAS | E91: {=INDEX(BASE!E:E,MATCH($A91,BASE!$A:$A,0))} -> 108676 | F91: {=INDEX(BASE!F:F,MATCH($A91,BASE!$A:$A,0))} -> FLOTA GONZALEZ , GLADYS DEL CARMEN | G91: {=INDEX(BASE!J:J,MATCH($A91,BASE!$A:$A,0))} -> 45876
A92: 88 | B92: 46073 | C92: Llamada efectiva (contestó) | D92: {=INDEX(BASE!$C:$C,MATCH($A92,BASE!$A:$A,0))} -> CARDENAS | E92: {=INDEX(BASE!E:E,MATCH($A92,BASE!$A:$A,0))} -> 106236 | F92: {=INDEX(BASE!F:F,MATCH($A92,BASE!$A:$A,0))} -> CRUZ MEJIA EDILIA | G92: {=INDEX(BASE!J:J,MATCH($A92,BASE!$A:$A,0))} -> 46024 | H92: no ha renobado con sus clientes, no ha buscado clientes nuevos | I92: 5 | K92: hay mas facilidades | L92: si | M92: es todo mas facil | N92: buscar clientes nuevos solo que tiene temor | O92: 1
A93: 89 | B93: 46073 | C93: No contestó | D93: {=INDEX(BASE!$C:$C,MATCH($A93,BASE!$A:$A,0))} -> CARDENAS | E93: {=INDEX(BASE!E:E,MATCH($A93,BASE!$A:$A,0))} -> 77044 | F93: {=INDEX(BASE!F:F,MATCH($A93,BASE!$A:$A,0))} -> AMALIA JUAREZ DE LOS SANTOS | G93: {=INDEX(BASE!J:J,MATCH($A93,BASE!$A:$A,0))} -> 46006
A94: 90 | B94: 46073 | C94: Se negó a contestar | D94: {=INDEX(BASE!$C:$C,MATCH($A94,BASE!$A:$A,0))} -> CARDENAS | E94: {=INDEX(BASE!E:E,MATCH($A94,BASE!$A:$A,0))} -> 112580 | F94: {=INDEX(BASE!F:F,MATCH($A94,BASE!$A:$A,0))} -> ARIAS CORDOVA , JUAN ANTONIO | G94: {=INDEX(BASE!J:J,MATCH($A94,BASE!$A:$A,0))} -> 46057
A95: 91 | B95: 46074 | C95: No contestó | D95: {=INDEX(BASE!$C:$C,MATCH($A95,BASE!$A:$A,0))} -> CARDENAS | E95: {=INDEX(BASE!E:E,MATCH($A95,BASE!$A:$A,0))} -> 77284 | F95: {=INDEX(BASE!F:F,MATCH($A95,BASE!$A:$A,0))} -> CANDELARIO ALCUDIA MONTIEL | G95: {=INDEX(BASE!J:J,MATCH($A95,BASE!$A:$A,0))} -> 46058
A96: 92 | B96: 46074 | C96: No contestó | D96: {=INDEX(BASE!$C:$C,MATCH($A96,BASE!$A:$A,0))} -> CARDENAS | E96: {=INDEX(BASE!E:E,MATCH($A96,BASE!$A:$A,0))} -> 104517 | F96: {=INDEX(BASE!F:F,MATCH($A96,BASE!$A:$A,0))} -> HERNANDEZ ALAMILLA SHEILA DEL CARMEN | G96: {=INDEX(BASE!J:J,MATCH($A96,BASE!$A:$A,0))} -> 46021
A97: 93 | B97: 46074 | C97: No contestó | D97: {=INDEX(BASE!$C:$C,MATCH($A97,BASE!$A:$A,0))} -> CARDENAS | E97: {=INDEX(BASE!E:E,MATCH($A97,BASE!$A:$A,0))} -> 105299 | F97: {=INDEX(BASE!F:F,MATCH($A97,BASE!$A:$A,0))} -> SANCHEZ MORENO BRISEIDA | G97: {=INDEX(BASE!J:J,MATCH($A97,BASE!$A:$A,0))} -> 46059
A98: 94 | B98: 46074 | C98: Buzón | D98: {=INDEX(BASE!$C:$C,MATCH($A98,BASE!$A:$A,0))} -> CARDENAS | E98: {=INDEX(BASE!E:E,MATCH($A98,BASE!$A:$A,0))} -> 109107 | F98: {=INDEX(BASE!F:F,MATCH($A98,BASE!$A:$A,0))} -> MONTEJO HERNANDEZ , MARIA ELENA | G98: {=INDEX(BASE!J:J,MATCH($A98,BASE!$A:$A,0))} -> 46057
A99: 95 | B99: 46074 | C99: Buzón | D99: {=INDEX(BASE!$C:$C,MATCH($A99,BASE!$A:$A,0))} -> CARDENAS | E99: {=INDEX(BASE!E:E,MATCH($A99,BASE!$A:$A,0))} -> 109709 | F99: {=INDEX(BASE!F:F,MATCH($A99,BASE!$A:$A,0))} -> CARRETA SILVAN , CECILIA DEL CARMEN | G99: {=INDEX(BASE!J:J,MATCH($A99,BASE!$A:$A,0))} -> 46057
A100: 96 | B100: 46074 | C100: No contestó | D100: {=INDEX(BASE!$C:$C,MATCH($A100,BASE!$A:$A,0))} -> CARDENAS | E100: {=INDEX(BASE!E:E,MATCH($A100,BASE!$A:$A,0))} -> 114020 | F100: {=INDEX(BASE!F:F,MATCH($A100,BASE!$A:$A,0))} -> RAMON SANCHEZ , SORAY DEL CARMEN | G100: {=INDEX(BASE!J:J,MATCH($A100,BASE!$A:$A,0))} -> 46002
A101: 97 | B101: 46074 | C101: Llamada efectiva (contestó) | D101: {=INDEX(BASE!$C:$C,MATCH($A101,BASE!$A:$A,0))} -> CARDENAS | E101: {=INDEX(BASE!E:E,MATCH($A101,BASE!$A:$A,0))} -> 113797 | F101: {=INDEX(BASE!F:F,MATCH($A101,BASE!$A:$A,0))} -> RAMOS HERNANDEZ , LUCIA | G101: {=INDEX(BASE!J:J,MATCH($A101,BASE!$A:$A,0))} -> 46059 | H101: no se quiere saturar de clientes, prefiere tener un mejor control | I101: 5 | K101: las comisiones son buenas | L101: si | M101: todo es digital y mas rapido | N101: meter mas clientes | O101: 1
...

Sheet Hoja1

Sheet BASE
A1: renglon | B1: region | C1: id_sucursal | D1: id_coordinador | E1: id_cliente | F1: Nombre | G1: Estatus | H1: TIPO | I1: fecha_alta | J1: fhUltimoCanje | K1: tipo.antiguedad | L1: %disponible | M1: tipo_colocado | N1: telefono | O1: telefono2
A2: 1 | B2: SUR | C2: ACAYUCAN | D2: 243 | E2: 86079 | F2: MARIA DE LOS ANGELES MEZA REYES | G2: ACTIVO | H2: DIAMANTE | I2: 44975 | J2: 46052 | K2: mas de 2.5 | L2: 72.463489 | M2: 46 a 60 dias | N2: 9241052982
A3: 2 | B3: SUR | C3: ACAYUCAN | D3: 1112 | E3: 86166 | F3: GABRIELA SANCHEZ GONZALEZ | G3: ACTIVO | H3: PLATA | I3: 45042 | J3: 46051 | K3: mas de 2.5 | L3: 97.000361 | M3: 106 a 120 dias | N3: 9241275593
A4: 3 | B4: SUR | C4: ACAYUCAN | D4: 243 | E4: 86052 | F4: MARIA DEL CARMEN CRUZ JIMENEZ | G4: ACTIVO | H4: ORO | I4: 44978 | J4: 46014 | K4: mas de 2.5 | L4: 74.160812 | M4: 46 a 60 dias | N4: 9241057172
A5: 4 | B5: SUR | C5: ACAYUCAN | D5: 1112 | E5: 109938 | F5: PEREZ HERNANDEZ , PETRONILA | G5: ACTIVO | H5: PLATA | I5: 45700 | J5: 46050 | K5: 6 A 1año | L5: 95.000971 | M5: 121 dias en adel | N5: 9241495415 | O5: 9241495415
A6: 5 | B6: SUR | C6: ACAYUCAN | D6: 1112 | E6: 86237 | F6: HERLINDA LOPEZ NO | G6: ACTIVO | H6: ORO | I6: 45187 | J6: 46054 | K6: 2 a 2.5años | L6: 60.324086 | M6: 30 a 45 dias | N6: 9241101679
A7: 6 | B7: SUR | C7: ACAYUCAN | D7: 1112 | E7: 116240 | F7: NOLASCO BLANCO , ERICK NAHIM | G7: ACTIVO | H7: PLATA | I7: 45990 | J7: 46050 | K7: 1 A 3MESES | L7: 93.001517 | M7: 30 a 45 dias | N7: 9241950524 | O7: 0
A8: 7 | B8: SUR | C8: ACAYUCAN | D8: 1112 | E8: 116013 | F8: HERNANDEZ MODESTO , ANA BEATRIZ | G8: ACTIVO | H8: PLATA | I8: 45981 | J8: 46028 | K8: 1 A 3MESES | L8: 91.750834 | M8: 30 a 45 dias | N8: 9731752583 | O8: 0
A9: 8 | B9: SUR | C9: ACAYUCAN | D9: 243 | E9: 86024 | F9: MARTHA REINA REYES GABINO | G9: ACTIVO | H9: ORO | I9: 44974 | J9: 45994 | K9: mas de 2.5 | L9: 69.051365 | M9: 61 a 75 dias | N9: 9241171656
A10: 9 | B10: SUR | C10: ACAYUCAN | D10: 243 | E10: 86065 | F10: NATALI DE MONSERRAT RUIZ VERGARA | G10: ACTIVO | H10: ORO | I10: 44978 | J10: 45994 | K10: mas de 2.5 | L10: 70.001736 | M10: 61 a 75 dias | N10: 9241050221
A11: 10 | B11: SUR | C11: ACAYUCAN | D11: 243 | E11: 86072 | F11: ELIZABETH GUILLEN FERNANDEZ | G11: ACTIVO | H11: PLATA | I11: 44980 | J11: 45962 | K11: mas de 2.5 | L11: 80.001132 | M11: 91 a 105 dias | N11: 9241070848
A12: 11 | B12: SUR | C12: ACAYUCAN | D12: 243 | E12: 86035 | F12: MARIA CRISTINA MUÑOZ CARDENAS | G12: ACTIVO | H12: ORO | I12: 45009 | J12: 46054 | K12: mas de 2.5 | L12: 61.329538 | M12: 61 a 75 dias | N12: 9241087001
A13: 12 | B13: SUR | C13: ACAYUCAN | D13: 1112 | E13: 109931 | F13: AGUIRRE ENRIQUEZ , GUADALUPE | G13: ACTIVO | H13: PLATA | I13: 45698 | J13: 46024 | K13: 6 A 1año | L13: 75.10129 | M13: 30 a 45 dias | N13: 9241349894 | O13: 9241349894
A14: 13 | B14: SUR | C14: ACAYUCAN | D14: 1112 | E14: 103239 | F14: TADEO ANTONIO EVA | G14: ACTIVO | H14: PLATA | I14: 45281 | J14: 46054 | K14: 2 a 2.5años | L14: 83.572242 | M14: 46 a 60 dias | N14: 9221592600 | O14: 0
A15: 14 | B15: SUR | C15: ACAYUCAN | D15: 243 | E15: 86105 | F15: ANGELICA TREJO PEREZ | G15: ACTIVO | H15: ORO | I15: 44974 | J15: 46045 | K15: mas de 2.5 | L15: 47.373964 | M15: 15 a 29 dias | N15: 9241387844
A16: 15 | B16: SUR | C16: ACAYUCAN | D16: 1112 | E16: 86149 | F16: PETRA RAMIREZ USCANGA | G16: ACTIVO | H16: ORO | I16: 45007 | J16: 46056 | K16: mas de 2.5 | L16: 56.107532 | M16: 30 a 45 dias | N16: 9241526974
A17: 16 | B17: SUR | C17: ACAYUCAN | D17: 243 | E17: 86041 | F17: ZORAIDA MENDOZA DE JESUS | G17: ACTIVO | H17: PLATA | I17: 44974 | J17: 46056 | K17: mas de 2.5 | L17: 81.444511 | M17: 91 a 105 dias | N17: 9241466507
A18: 17 | B18: SUR | C18: ACAYUCAN | D18: 243 | E18: 86053 | F18: NICOLASA HERNANDEZ MARTINEZ | G18: ACTIVO | H18: PLATA | I18: 44978 | J18: 45980 | K18: mas de 2.5 | L18: 90.000714 | M18: 76 a 90 dias | N18: 9241331245
A19: 18 | B19: SUR | C19: ACAYUCAN | D19: 243 | E19: 86037 | F19: ANA LUISA ZENTENO MARTINEZ | G19: ACTIVO | H19: PLATA | I19: 44979 | J19: 46003 | K19: mas de 2.5 | L19: 62.560448 | M19: 46 a 60 dias | N19: 9241058513
A20: 19 | B20: SUR | C20: ACAYUCAN | D20: 243 | E20: 116138 | F20: GUILLEN SANTIAGO , ALONDRA | G20: ACTIVO | H20: PLATA | I20: 45986 | J20: 45997 | K20: 1 A 3MESES | L20: 87.501349 | M20: 61 a 75 dias | N20: 9241492568 | O20: 0
A21: 20 | B21: SUR | C21: ACAYUCAN | D21: 243 | E21: 86083 | F21: DORA PEREZ GOMEZ | G21: ACTIVO | H21: PLATA | I21: 44974 | J21: 46017 | K21: mas de 2.5 | L21: 52.502849 | M21: 30 a 45 dias | N21: 9241272818
A22: 21 | B22: SUR | C22: ACAYUCAN | D22: 243 | E22: 103924 | F22: CORDERO RAMIREZ MARIBEL | G22: ACTIVO | H22: PLATA | I22: 45332 | J22: 45965 | K22: 1.5 a 2años | L22: 90.00092 | M22: 91 a 105 dias | N22: 9242102229 | O22: 0
A23: 22 | B23: SUR | C23: ACAYUCAN | D23: 243 | E23: 107170 | F23: ISIDORO CANDIDO , ALEJANDRA | G23: ACTIVO | H23: PLATA | I23: 45516 | J23: 45962 | K23: 1 a 1.5años | L23: 94.444956 | M23: 91 a 105 dias | N23: 9241172455 | O23: 9241172455
A24: 23 | B24: SUR | C24: ACAYUCAN | D24: 243 | E24: 110417 | F24: PULIDO LICONA , VERONICA | G24: ACTIVO | H24: PLATA | I24: 45734 | J24: 46003 | K24: 6 A 1año | L24: 68.57574 | M24: 46 a 60 dias | N24: 9242101661 | O24: 9242101661
A25: 24 | B25: SUR | C25: ACAYUCAN | D25: 1112 | E25: 108567 | F25: DOMINGUEZ ALFONSO , MARIA ELENA | G25: ACTIVO | H25: PLATA | I25: 45593 | J25: 46054 | K25: 1 a 1.5años | L25: 46.673452 | M25: 46 a 60 dias | N25: 9241293751 | O25: 0
A26: 25 | B26: NORESTE | C26: ALTAMIRA | D26: 1149 | E26: 57216 | F26: MARIA GUADALUPE AQUINO BANDA | G26: ACTIVO | H26: DIAMANTE | I26: 44432 | J26: 45909 | K26: mas de 2.5 | L26: 98.561209 | M26: 121 dias en adel | N26: 8331821626
A27: 26 | B27: NORESTE | C27: ALTAMIRA | D27: 1149 | E27: 57064 | F27: MARIA CONCEPCION LOREDO AVALOS | G27: ACTIVO | H27: DIAMANTE VIP | I27: 44126 | J27: 45981 | K27: mas de 2.5 | L27: 68.518903 | M27: 76 a 90 dias | N27: 8331287549
A28: 27 | B28: NORESTE | C28: ALTAMIRA | D28: 1149 | E28: 57306 | F28: BERENICE SEGURA DEL ANGEL | G28: ACTIVO | H28: DIAMANTE VIP | I28: 44691 | J28: 46022 | K28: mas de 2.5 | L28: 58.129837 | M28: 30 a 45 dias | N28: 8332065948
A29: 28 | B29: NORESTE | C29: ALTAMIRA | D29: 160 | E29: 57403 | F29: JOSE LUIS GUZMAN MADRIGALES | G29: ACTIVO | H29: DIAMANTE | I29: 44946 | J29: 46021 | K29: mas de 2.5 | L29: 64.809509 | M29: 30 a 45 dias | N29: 8333674373
A30: 29 | B30: NORESTE | C30: ALTAMIRA | D30: 1149 | E30: 57363 | F30: GUADALUPE FLORES GUZMAN | G30: ACTIVO | H30: PLATINO | I30: 44837 | J30: 45938 | K30: mas de 2.5 | L30: 96.840713 | M30: 121 dias en adel | N30: 8334261212
A31: 30 | B31: NORESTE | C31: ALTAMIRA | D31: 1285 | E31: 104106 | F31: GERONIMO FRANCO DORA ALICIA | G31: ACTIVO | H31: DIAMANTE | I31: 45345 | J31: 46058 | K31: 1.5 a 2años | L31: 55.571439 | M31: 46 a 60 dias | N31: 8331060482 | O31: 0
A32: 31 | B32: NORESTE | C32: ALTAMIRA | D32: 1149 | E32: 57088 | F32: MARIA VICTORIA GARCIA SOLIS | G32: ACTIVO | H32: ORO | I32: 44144 | J32: 45967 | K32: mas de 2.5 | L32: 93.667007 | M32: 91 a 105 dias | N32: 8334364867
A33: 32 | B33: NORESTE | C33: ALTAMIRA | D33: 160 | E33: 57290 | F33: NORMA ELIZABETH SALAS MAR | G33: ACTIVO | H33: PLATINO | I33: 44673 | J33: 46059 | K33: mas de 2.5 | L33: 55.541202 | M33: 15 a 29 dias | N33: 8333391534
A34: 33 | B34: NORESTE | C34: ALTAMIRA | D34: 160 | E34: 57243 | F34: CLARABELLA HERNANDEZ ALONSO | G34: ACTIVO | H34: ORO | I34: 44604 | J34: 45980 | K34: mas de 2.5 | L34: 84.070146 | M34: 76 a 90 dias | N34: 8333223438
A35: 34 | B35: NORESTE | C35: ALTAMIRA | D35: 160 | E35: 57212 | F35: EDUVIGES RODRIGUEZ PONCE | G35: ACTIVO | H35: PLATINO | I35: 44620 | J35: 46021 | K35: mas de 2.5 | L35: 54.845562 | M35: 30 a 45 dias | N35: 8332040294
A36: 35 | B36: NORESTE | C36: ALTAMIRA | D36: 160 | E36: 106746 | F36: YAÑEZ MARTINEZ , MARIA LOURDES | G36: ACTIVO | H36: PLATA | I36: 45488 | J36: 45925 | K36: 1.5 a 2años | L36: 91.667234 | M36: 121 dias en adel | N36: 8334121349 | O36: 0
A37: 36 | B37: NORESTE | C37: ALTAMIRA | D37: 1285 | E37: 110263 | F37: CAMPOZANO FLORES , ELENA | G37: ACTIVO | H37: ORO | I37: 45723 | J37: 46058 | K37: 6 A 1año | L37: 64.858864 | M37: 30 a 45 dias | N37: 8334279329 | O37: 0
A38: 37 | B38: NORESTE | C38: ALTAMIRA | D38: 160 | E38: 57299 | F38: VICTORIA LARA ZARAGOZA | G38: ACTIVO | H38: PLATINO | I38: 44728 | J38: 46053 | K38: mas de 2.5 | L38: 48.540516 | M38: 30 a 45 dias | N38: 8332844530
A39: 38 | B39: NORESTE | C39: ALTAMIRA | D39: 160 | E39: 113504 | F39: SOBREVILLA PEREZ , AURORA | G39: ACTIVO | H39: ORO | I39: 45887 | J39: 46007 | K39: 3 A 6MESES | L39: 61.43262 | M39: 46 a 60 dias | N39: 8333419217 | O39: 0
A40: 39 | B40: NORESTE | C40: ALTAMIRA | D40: 1149 | E40: 57345 | F40: ANA MARISELA SILVA HERNANDEZ | G40: ACTIVO | H40: ORO | I40: 44782 | J40: 46024 | K40: mas de 2.5 | L40: 52.446893 | M40: 30 a 45 dias | N40: 8332396089
A41: 40 | B41: NORESTE | C41: ALTAMIRA | D41: 160 | E41: 115703 | F41: ANDONEY SANTIAGO , TERESA | G41: ACTIVO | H41: PLATA | I41: 45971 | J41: 46007 | K41: 1 A 3MESES | L41: 76.002995 | M41: 46 a 60 dias | N41: 8333408365 | O41: 0
A42: 41 | B42: NORESTE | C42: ALTAMIRA | D42: 160 | E42: 57225 | F42: MARTHA PATRICIA LOZANO RIVAS | G42: ACTIVO | H42: PLATA | I42: 44533 | J42: 45981 | K42: mas de 2.5 | L42: 75.866472 | M42: 76 a 90 dias | N42: 8335346271 | O42: 8333626234
A43: 42 | B43: NORESTE | C43: ALTAMIRA | D43: 1149 | E43: 57163 | F43: VILLALOBOS ARIAS , AMANDA | G43: ACTIVO | H43: PLATA | I43: 44236 | J43: 46052 | K43: mas de 2.5 | L43: 67.003544 | M43: 46 a 60 dias | N43: 8333881621 | O43: 0
A44: 43 | B44: NORESTE | C44: ALTAMIRA | D44: 160 | E44: 57371 | F44: REBOLLAR TORRES , NANCY MARGARITA | G44: ACTIVO | H44: PLATA | I44: 1 | J44: 46058 | K44: mas de 2.5 | L44: 50.555028 | M44: 30 a 45 dias | N44: 8338447740 | O44: 0
A45: 44 | B45: NORESTE | C45: ALTAMIRA | D45: 160 | E45: 57276 | F45: MARTHA PECERO HERNANDEZ | G45: ACTIVO | H45: PLATA | I45: 44659 | J45: 46009 | K45: mas de 2.5 | L45: 47.359003 | M45: 46 a 60 dias | N45: 8336955535
A46: 45 | B46: NORESTE | C46: ALTAMIRA | D46: 160 | E46: 107732 | F46: VIGIL IBARRA , EUNICE | G46: ACTIVO | H46: PLATINO | I46: 45544 | J46: 46057 | K46: 1 a 1.5años | L46: 13.720173 | M46: 30 a 45 dias | N46: 8335143760 | O46: 0
A47: 46 | B47: CENTRO | C47: BAHIA | D47: 1205 | E47: 105647 | F47: TAPIA MARIN KARLA CAROLINA | G47: ACTIVO | H47: DIAMANTE | I47: 45437 | J47: 46056 | K47: 1.5 a 2años | L47: 77.117367 | M47: 30 a 45 dias | N47: 3222390874 | O47: 0
A48: 47 | B48: CENTRO | C48: BAHIA | D48: 1205 | E48: 32148 | F48: GRACIELA VALENZUELA RODRIGUEZ | G48: ACTIVO | H48: PLATINO | I48: 44066 | J48: 46057 | K48: mas de 2.5 | L48: 61.598283 | M48: 30 a 45 dias | N48: 3221835986 | O48: 3221835986
A49: 48 | B49: CENTRO | C49: BAHIA | D49: 1205 | E49: 108163 | F49: IBARRA CARO , NADIA LIZBETH | G49: ACTIVO | H49: PLATINO | I49: 45570 | J49: 45988 | K49: 1 a 1.5años | L49: 69.975613 | M49: 61 a 75 dias | N49: 3221937145 | O49: 0
A50: 49 | B50: CENTRO | C50: BAHIA | D50: 1205 | E50: 112573 | F50: RODRIGUEZ GUZMAN , ANAHI GUADALUPE | G50: ACTIVO | H50: PLATA | I50: 45843 | J50: 45911 | K50: 6 A 1año | L50: 97.381275 | M50: 121 dias en adel | N50: 3221986927 | O50: 0
A51: 50 | B51: CENTRO | C51: BAHIA | D51: 1205 | E51: 106982 | F51: RAMIREZ HERNANDEZ MA. ESTHER | G51: ACTIVO | H51: ORO | I51: 45503 | J51: 45944 | K51: 1.5 a 2años | L51: 81.654431 | M51: 106 a 120 dias | N51: 3222700394 | O51: 0
A52: 51 | B52: CENTRO | C52: BAHIA | D52: 1205 | E52: 104785 | F52: GOMEZ GARCIA TOMAS | G52: ACTIVO | H52: PLATINO | I52: 45389 | J52: 46024 | K52: 1.5 a 2años | L52: 63.632838 | M52: 30 a 45 dias | N52: 3221372267 | O52: 0
A53: 52 | B53: CENTRO | C53: BAHIA | D53: 1205 | E53: 106099 | F53: ESPARZA ALVAREZ DAIRA LIZETTE | G53: ACTIVO | H53: ORO | I53: 45454 | J53: 45997 | K53: 1.5 a 2años | L53: 84.102255 | M53: 61 a 75 dias | N53: 3223267293 | O53: 0
A54: 53 | B54: CENTRO | C54: BAHIA | D54: 1205 | E54: 113002 | F54: CORTEZ MENDOZA , ALEXANDRA | G54: ACTIVO | H54: PLATA | I54: 45867 | J54: 45943 | K54: 6 A 1año | L54: 93.179347 | M54: 106 a 120 dias | N54: 9848010778 | O54: 0
A55: 54 | B55: CENTRO | C55: BAHIA | D55: 1205 | E55: 105186 | F55: BELLO SANTIAGO HORTENCIA | G55: ACTIVO | H55: PLATA | I55: 45407 | J55: 45945 | K55: 1.5 a 2años | L55: 90.000861 | M55: 106 a 120 dias | N55: 3222054625 | O55: 0
A56: 55 | B56: CENTRO | C56: BAHIA | D56: 1205 | E56: 115750 | F56: CONTRERAS CRUZ , LUIS ARMANDO | G56: ACTIVO | H56: PLATA | I56: 45972 | J56: 46009 | K56: 1 A 3MESES | L56: 86.002865 | M56: 46 a 60 dias | N56: 3223048770 | O56: 0
A57: 56 | B57: CENTRO | C57: BAHIA | D57: 211 | E57: 116863 | F57: TAGLE VALENTE , DAMARIS YUNUEN | G57: ACTIVO | H57: PLATA | I57: 46020 | J57: 46049 | K57: 1 A 3MESES | L57: 81.667972 | M57: 30 a 45 dias | N57: 3228887818 | O57: 0
... A64: 63 | B64: SUR | C64: CARDENAS | D64: 1091 | E64: 77003 | F64: ENEIDA PEREZ GARCIA | G64: ACTIVO | H64: PLATINO | I64: 44867 | J64: 45991 | K64: mas de 2.5 | L64: 86.787998 | M64: 61 a 75 dias | N64: 9371242325 | O64: 9371242325
A65: 64 | B65: SUR | C65: CARDENAS | D65: 1091 | E65: 77063 | F65: GUADALUPE RIVERA SANCHEZ | G65: ACTIVO | H65: PLATINO | I65: 44882 | J65: 45964 | K65: mas de 2.5 | L65: 82.135328 | M65: 91 a 105 dias | N65: 9372704116
A66: 65 | B66: SUR | C66: CARDENAS | D66: 1091 | E66: 77066 | F66: ADRIANA GAMAS QUIROGA | G66: ACTIVO | H66: DIAMANTE | I66: 44894 | J66: 46055 | K66: mas de 2.5 | L66: 65.126628 | M66: 46 a 60 dias | N66: 9373773579
A67: 66 | B67: SUR | C67: CARDENAS | D67: 1091 | E67: 77176 | F67: GLORIA DEL JESUS JIMENEZ HIDALGO | G67: ACTIVO | H67: DIAMANTE | I67: 44971 | J67: 46030 | K67: mas de 2.5 | L67: 52.003019 | M67: 30 a 45 dias | N67: 9371289195
A68: 67 | B68: SUR | C68: CARDENAS | D68: 1101 | E68: 105314 | F68: FLORES GOMEZ CINDY RUBI | G68: ACTIVO | H68: PLATINO | I68: 45409 | J68: 46054 | K68: 1.5 a 2años | L68: 59.20725 | M68: 30 a 45 dias | N68: 9372288931 | O68: 0
A69: 68 | B69: SUR | C69: CARDENAS | D69: 1286 | E69: 77020 | F69: DANELLI LOPEZ MARTINEZ | G69: ACTIVO | H69: PLATINO | I69: 44875 | J69: 46049 | K69: mas de 2.5 | L69: 75.659032 | M69: 30 a 45 dias | N69: 9371213334 | O69: 9371213334
A70: 69 | B70: SUR | C70: CARDENAS | D70: 1101 | E70: 108220 | F70: OLAN GARCIA , YOSHIO | G70: ACTIVO | H70: ORO | I70: 45572 | J70: 46051 | K70: 1 a 1.5años | L70: 83.67271 | M70: 76 a 90 dias | N70: 9371170105 | O70: 0
A71: 70 | B71: SUR | C71: CARDENAS | D71: 1101 | E71: 105585 | F71: DE LA CRUZ ZAMORA LIDIA DEL CARMEN | G71: ACTIVO | H71: ORO | I71: 45422 | J71: 45916 | K71: 1.5 a 2años | L71: 96.207946 | M71: 121 dias en adel | N71: 9171082272 | O71: 0
A72: 71 | B72: SUR | C72: CARDENAS | D72: 1286 | E72: 77202 | F72: ESTRELLA OLAN ALEGRIA | G72: ACTIVO | H72: PLATA | I72: 45010 | J72: 45936 | K72: mas de 2.5 | L72: 98.392869 | M72: 121 dias en adel | N72: 8114866400
A73: 72 | B73: SUR | C73: CARDENAS | D73: 1101 | E73: 106979 | F73: DE LA CRUZ GOMEZ , DOLORES | G73: ACTIVO | H73: DIAMANTE | I73: 45502 | J73: 46054 | K73: 1.5 a 2años | L73: 38.759329 | M73: 30 a 45 dias | N73: 9935146228 | O73: 0
A74: 73 | B74: SUR | C74: CARDENAS | D74: 1101 | E74: 117047 | F74: CALIX GOMEZ , YENI | G74: ACTIVO | H74: PLATA | I74: 46028 | J74: 46055 | K74: 16 a 30 Dias | L74: 100 | M74: 0 | N74: 9371167222 | O74: 0
A75: 74 | B75: SUR | C75: CARDENAS | D75: 1286 | E75: 109597 | F75: FUENTES HERNANDEZ , CAROLINA | G75: ACTIVO | H75: PLATA | I75: 45674 | J75: 45881 | K75: 1 a 1.5años | L75: 95.83354 | M75: 121 dias en adel | N75: 9371669302 | O75: 9371669302
A76: 75 | B76: SUR | C76: CARDENAS | D76: 1286 | E76: 109448 | F76: DE LA CRUZ SAUZ , CARLOS | G76: ACTIVO | H76: PLATA | I76: 45663 | J76: 46058 | K76: 1 a 1.5años | L76: 94.066932 | M76: 121 dias en adel | N76: 9371182462 | O76: 9371182462
A77: 76 | B77: SUR | C77: CARDENAS | D77: 1091 | E77: 103951 | F77: REYES RODRIGUEZ CLARA AURORA | G77: ACTIVO | H77: ORO | I77: 45362 | J77: 46053 | K77: 1.5 a 2años | L77: 71.980286 | M77: 30 a 45 dias | N77: 9373780853 | O77: 0
A78: 77 | B78: SUR | C78: CARDENAS | D78: 1101 | E78: 108635 | F78: DOMINGUEZ HERNANDEZ , GUADALUPE | G78: ACTIVO | H78: ORO | I78: 45600 | J78: 46052 | K78: 1 a 1.5años | L78: 58.546622 | M78: 30 a 45 dias | N78: 9371304201 | O78: 9371304201
A79: 78 | B79: SUR | C79: CARDENAS | D79: 1091 | E79: 116912 | F79: BLANCO SOSA , ANAHI | G79: ACTIVO | H79: PLATA | I79: 46021 | J79: 46049 | K79: 16 a 30 Dias | L79: 90.834328 | M79: 30 a 45 dias | N79: 9934754884 | O79: 0
A80: 79 | B80: SUR | C80: CARDENAS | D80: 1101 | E80: 116732 | F80: ESPITIA SANTOS , SANDY | G80: ACTIVO | H80: PLATA | I80: 46010 | J80: 46014 | K80: 1 A 3MESES | L80: 90.00156 | M80: 46 a 60 dias | N80: 9371277759 | O80: 0
A81: 80 | B81: SUR | C81: CARDENAS | D81: 1091 | E81: 106130 | F81: PINEDA PALMA FABIOLA | G81: ACTIVO | H81: PLATA | I81: 45458 | J81: 45979 | K81: 1.5 a 2años | L81: 88.801818 | M81: 76 a 90 dias | N81: 9171098714 | O81: 0
A82: 81 | B82: SUR | C82: CARDENAS | D82: 1286 | E82: 109300 | F82: PINEDA ALEJANDRO , VIVIANA | G82: ACTIVO | H82: PLATA | I82: 45642 | J82: 46014 | K82: 1 a 1.5años | L82: 73.003304 | M82: 46 a 60 dias | N82: 9371511079 | O82: 9371511079
A83: 82 | B83: SUR | C83: CARDENAS | D83: 1286 | E83: 77185 | F83: MARIA CRISTINA QUETCHUM JIMENEZ | G83: ACTIVO | H83: ORO | I83: 44982 | J83: 46027 | K83: mas de 2.5 | L83: 60.994099 | M83: 30 a 45 dias | N83: 9371830041 | O83: 9371830041
A84: 83 | B84: SUR | C84: CARDENAS | D84: 1091 | E84: 112110 | F84: ESCALANTE LOPEZ , NIDIA MARIA | G84: ACTIVO | H84: ORO | I84: 45819 | J84: 46022 | K84: 6 A 1año | L84: 61.384816 | M84: 30 a 45 dias | N84: 9371342094 | O84: 0
A85: 84 | B85: SUR | C85: CARDENAS | D85: 1091 | E85: 116399 | F85: REYES DE LA CRUZ , ISABEL | G85: ACTIVO | H85: PLATA | I85: 45996 | J85: 46011 | K85: 1 A 3MESES | L85: 78.402246 | M85: 46 a 60 dias | N85: 9371686194 | O85: 9371686194
A86: 85 | B86: SUR | C86: CARDENAS | D86: 1091 | E86: 113201 | F86: JIMENEZ GOMEZ , BELEM | G86: ACTIVO | H86: PLATA | I86: 45874 | J86: 45875 | K86: 3 A 6MESES | L86: 97.857967 | M86: 121 dias en adel | N86: 9371717893 | O86: 0
... A91: 90 | B91: SUR | C91: CARDENAS | D91: 1101 | E91: 112580 | F91: ARIAS CORDOVA , JUAN ANTONIO | G91: ACTIVO | H91: PLATA | I91: 45844 | J91: 46057 | K91: 6 A 1año | L91: 64.409092 | M91: 30 a 45 dias | N91: 9371005540 | O91: 9371005540
A92: 91 | B92: SUR | C92: CARDENAS | D92: 1286 | E92: 77284 | F92: CANDELARIO ALCUDIA MONTIEL | G92: ACTIVO | H92: PLATA | I92: 45187 | J92: 46058 | K92: 2 a 2.5años | L92: 76.025047 | M92: 91 a 105 dias | N92: 9371414460
A93: 92 | B93: SUR | C93: CARDENAS | D93: 1286 | E93: 104517 | F93: HERNANDEZ ALAMILLA SHEILA DEL CARMEN | G93: ACTIVO | H93: PLATA | I93: 45371 | J93: 46021 | K93: 1.5 a 2años | L93: 58.968621 | M93: 30 a 45 dias | N93: 9371269066 | O93: 9371252550
A94: 93 | B94: SUR | C94: CARDENAS | D94: 1101 | E94: 105299 | F94: SANCHEZ MORENO BRISEIDA | G94: ACTIVO | H94: PLATINO | I94: 45408 | J94: 46059 | K94: 1.5 a 2años | L94: 26.605652 | M94: 30 a 45 dias | N94: 9171164295 | O94: 0
A95: 94 | B95: SUR | C95: CARDENAS | D95: 1091 | E95: 109107 | F95: MONTEJO HERNANDEZ , MARIA ELENA | G95: ACTIVO | H95: PLATA | I95: 45628 | J95: 46057 | K95: 1 a 1.5años | L95: 57.669329 | M95: 30 a 45 dias | N95: 9371675638 | O95: 0
A96: 95 | B96: SUR | C96: CARDENAS | D96: 1091 | E96: 109709 | F96: CARRETA SILVAN , CECILIA DEL CARMEN | G96: ACTIVO | H96: ORO | I96: 45682 | J96: 46057 | K96: 1 a 1.5años | L96: 43.686363 | M96: 30 a 45 dias | N96: 3331378047 | O96: 3331378047
A97: 96 | B97: SUR | C97: CARDENAS | D97: 1091 | E97: 114020 | F97: RAMON SANCHEZ , SORAY DEL CARMEN | G97: ACTIVO | H97: PLATA | I97: 45910 | J97: 46002 | K97: 3 A 6MESES | L97: 46.395252 | M97: 46 a 60 dias | N97: 9371714308 | O97: 9371714308
A98: 97 | B98: SUR | C98: CARDENAS | D98: 1091 | E98: 113797 | F98: RAMOS HERNANDEZ , LUCIA | G98: ACTIVO | H98: PLATA | I98: 45899 | J98: 46059 | K98: 3 A 6MESES | L98: 42.947288 | M98: 30 a 45 dias | N98: 9371252077 | O98: 0
A99: 98 | B99: SUR | C99: CARDENAS | D99: 1101 | E99: 108522 | F99: BUSTAMANTE ESCUDERO , MARIA CRISTI | G99: ACTIVO | H99: PLATA | I99: 45593 | J99: 45969 | K99: 1 a 1.5años | L99: 83.500968 | M99: 91 a 105 dias | N99: 9371404718 | O99: 9371404718
A100: 99 | B100: SUR | C100: CARDENAS | D100: 1286 | E100: 105090 | F100: PEREZ HERNANDEZ ANA AGUSTINA | G100: ACTIVO | H100: ORO | I100: 45401 | J100: 46051 | K100: 1.5 a 2años | L100: 38.943957 | M100: 30 a 45 dias | N100: 9931933989 | O100: 0
A101: 100 | B101: SUR | C101: CARDENAS | D101: 1091 | E101: 114893 | F101: MARTINEZ ALPUCHE , YESENIA | G101: ACTIVO | H101: PLATA | I101: 45944 | J101: 46028 | K101: 3 A 6MESES | L101: 41.689208 | M101: 30 a 45 dias | N101: 9371160205 | O101: 9371160205
A102: 101 | B102: SUR | C102: CARDENAS | D102: 1101 | E102: 109194 | F102: RINCON OVANDO , DIANA CRISTHELL | G102: ACTIVO | H102: ORO | I102: 45635 | J102: 46056 | K102: 1 a 1.5años | L102: 23.514754 | M102: 30 a 45 dias | N102: 9371105774 | O102: 0
A103: 102 | B103: SUR | C103: CARDENAS | D103: 1286 | E103: 104094 | F103: CORDOVA LEYVA ALICIA | G103: ACTIVO | H103: PLATINO | I103: 45343 | J103: 46057 | K103: 1.5 a 2años | L103: 16.462857 | M103: 30 a 45 dias | N103: 9371045695 | O103: 0
A104: 103 | B104: SUR | C104: CARDENAS | D104: 1286 | E104: 77215 | F104: ANALID VIDAL GONZALEZ | G104: ACTIVO | H104: PLATA | I104: 45028 | J104: 45996 | K104: mas de 2.5 | L104: 32.96578 | M104: 61 a 75 dias | N104: 9371530541 | O104: 9371530541
... A120: 119 | B120: CHIHUAHUA | C120: CHIHUAHUA | D120: 1273 | E120: 106939 | F120: RIVERA ALMANZA , ANA PAOLA | G120: ACTIVO | H120: PLATINO | I120: 45507 | J120: 45988 | K120: 1.5 a 2años | L120: 70.672945 | M120: 61 a 75 dias | N120: 6141677255 | O120: 0
A121: 120 | B121: CHIHUAHUA | C121: CHIHUAHUA | D121: 1181 | E121: 96109 | F121: SOCORRO GALVAN RODRIGUEZ | G121: ACTIVO | H121: ORO | I121: 45135 | J121: 46010 | K121: mas de 2.5 | L121: 84.445407 | M121: 46 a 60 dias | N121: 6141685964
A122: 121 | B122: CHIHUAHUA | C122: CHIHUAHUA | D122: 1273 | E122: 115660 | F122: FIERRO GONZALEZ , LUZ ESTHER | G122: ACTIVO | H122: PLATA | I122: 45969 | J122: NULL | K122: 1 A 3MESES | L122: 100 | M122: 0 | N122: 6141330081 | O122: 0
A123: 122 | B123: CHIHUAHUA | C123: CHIHUAHUA | D123: 1181 | E123: 114458 | F123: MENDOZA CORDERO , ELOISA | G123: ACTIVO | H123: PLATA | I123: 45929 | J123: 45930 | K123: 3 A 6MESES | L123: 94.444555 | M123: 121 dias en adel | N123: 6141164690 | O123: 0
A124: 123 | B124: CHIHUAHUA | C124: CHIHUAHUA | D124: 1181 | E124: 102488 | F124: CORTEZ SIFUENTES AURORA ISABEL | G124: ACTIVO | H124: ORO | I124: 45227 | J124: 46053 | K124: 2 a 2.5años | L124: 77.810559 | M124: 46 a 60 dias | N124: 6141836507 | O124: 0
A125: 124 | B125: CHIHUAHUA | C125: CHIHUAHUA | D125: 1273 | E125: 113543 | F125: ZEPEDA GONZALEZ , BRENDA SUGEY | G125: ACTIVO | H125: ORO | I125: 45888 | J125: 45979 | K125: 3 A 6MESES | L125: 76.771658 | M125: 76 a 90 dias | N125: 6143765236 | O125: 0
...

Sheet Hoja2
A1: id_cliente | B1: nombre | C1: Estatus | D1: TIPO | E1: limite | F1: DISPONIBLE | G1: SALDO | H1: Bolsa | I1: Disponible_Bolsa | J1: telefono | K1: telefono2
A2: 103239 | B2: TADEO ANTONIO EVA | C2: ACTIVO | D2: PLATA | E2: 8000 | F2: 625.3709 | G2: 13992.645 | H2: 1446 | I2: 0 | J2: 9221592600
A3: 103924 | B3: CORDERO RAMIREZ MARIBEL | C3: ACTIVO | D3: PLATA | E3: 12000 | F3: 11000.476 | G3: 1639.37 | H3: 1855 | I3: 0 | J3: 9242102229
A4: 107170 | B4: ISIDORO CANDIDO , ALEJANDRA | C4: ACTIVO | D4: PLATA | E4: 18000 | F4: 17400.104 | G4: 983.92 | H4: 1905 | I4: 0 | J4: 9241172455 | K4: 9241172455
A5: 107587 | B5: RODRIGUEZ PEREZ , BERENICE | C5: ACTIVO | D5: PLATA | E5: 43000 | F5: 8049.4267 | G5: 55200.43 | H5: 2177 | I5: 0 | J5: 2941551322 | K5: 2941551322
A6: 108567 | B6: DOMINGUEZ ALFONSO , MARIA ELENA | C6: ACTIVO | D6: PLATA | E6: 30000 | F6: 8177.492 | G6: 35967.25 | H6: 1968 | I6: 0 | J6: 9241293751
A7: 109931 | B7: AGUIRRE ENRIQUEZ , GUADALUPE | C7: ACTIVO | D7: PLATA | E7: 50000 | F7: 41286.141 | G7: 13419 | H7: 1351 | I7: 0 | J7: 9241349894 | K7: 9241349894
A8: 109938 | B8: PEREZ HERNANDEZ , PETRONILA | C8: ACTIVO | D8: PLATA | E8: 50000 | F8: 43034.308 | G8: 10863.42 | H8: 876 | I8: 0 | J8: 9241495415 | K8: 9241495415
A9: 110417 | B9: PULIDO LICONA , VERONICA | C9: ACTIVO | D9: PLATA | E9: 13000 | F9: 8200.8437 | G9: 7415.26 | H9: 1954 | I9: 0 | J9: 9242101661 | K9: 9242101661
A10: 116013 | B10: HERNANDEZ MODESTO , ANA BEATRIZ | C10: ACTIVO | D10: PLATA | E10: 50000 | F10: 47125.29 | G10: 4371 | H10: 955 | I10: 0 | J10: 9731752583
A11: 116138 | B11: GUILLEN SANTIAGO , ALONDRA | C11: ACTIVO | D11: PLATA | E11: 10000 | F11: 7750.7786 | G11: 3428.1 | H11: 1704 | I11: 0 | J11: 9241492568
A12: 116240 | B12: NOLASCO BLANCO , ERICK NAHIM | C12: ACTIVO | D12: PLATA | E12: 50000 | F12: 30476.985 | G12: 29980.33 | H12: 931 | I12: 0 | J12: 9241950524
A13: 86024 | B13: MARTHA REINA REYES GABINO | C13: ACTIVO | D13: ORO | E13: 63000 | F13: 50701.215 | G13: 19117 | H13: 1093 | I13: 0 | J13: (924) 117-1656 | K13: ( ) -
A14: 86035 | B14: MARIA CRISTINA MUÑOZ CARDENAS | C14: ACTIVO | D14: ORO | E14: 64600 | F14: 38752.198 | G14: 42408.09 | H14: 1256 | I14: 0 | J14: (924) 108-7001 | K14: ( ) -
A15: 86037 | B15: ANA LUISA ZENTENO MARTINEZ | C15: ACTIVO | D15: PLATA | E15: 43000 | F15: 32134.215 | G15: 17322.51 | H15: 1687 | I15: 0 | J15: (924) 105-8513 | K15: ( ) -
A16: 86041 | B16: ZORAIDA MENDOZA DE JESUS | C16: ACTIVO | D16: PLATA | E16: 35000 | F16: 25251.342 | G16: 15170.34 | H16: 1641 | I16: 0 | J16: (924) 146-6507 | K16: ( ) -
A17: 86052 | B17: MARIA DEL CARMEN CRUZ JIMENEZ | C17: ACTIVO | D17: ORO | E17: 65000 | F17: 54004.557 | G17: 17246.28 | H17: 833 | I17: 0 | J17: (924) 105-7172 | K17: ( ) -
A18: 86053 | B18: NICOLASA HERNANDEZ MARTINEZ | C18: ACTIVO | D18: PLATA | E18: 30000 | F18: 28400.554 | G18: 2519.21 | H18: 1684 | I18: 0 | J18: (924) 133-1245 | K18: ( ) -
A19: 86065 | B19: NATALI DE MONSERRAT RUIZ VERGARA | C19: ACTIVO | D19: ORO | E19: 60000 | F19: 45429.276 | G19: 26009.86 | H19: 1153 | I19: 0 | J19: (924) 105-0221 | K19: ( ) -
A20: 86071 | B20: SILVIA GUADALUPE GONZALEZ MORTERA | C20: ACTIVO | D20: PLATA | E20: 53000 | F20: 44652.847 | G20: 31701.465 | H20: #N/A | I20: 0 | J20: (924) 114-6171 | K20: ( ) -
A21: 86072 | B21: ELIZABETH GUILLEN FERNANDEZ | C21: ACTIVO | D21: PLATA | E21: 50000 | F21: 46000.634 | G21: 6239.26 | H21: 1238 | I21: 0 | J21: (924) 107-0848 | K21: ( ) -
A22: 86079 | B22: MARIA DE LOS ANGELES MEZA REYES | C22: ACTIVO | D22: DIAMANTE | E22: 126001 | F22: 87908.6 | G22: 59338.13 | H22: 169 | I22: 0 | J22: (924) 105-2982 | K22: ( ) -
A23: 86083 | B23: DORA PEREZ GOMEZ | C23: ACTIVO | D23: PLATA | E23: 42000 | F23: 29051.052 | G23: 23351.87 | H23: 1812 | I23: 0 | J23: (924) 127-2818 | K23: ( ) -
A24: 86105 | B24: ANGELICA TREJO PEREZ | C24: ACTIVO | D24: ORO | E24: 64697 | F24: 39598.995 | G24: 39019.28 | H24: 1579 | I24: 0 | J24: (924) 138-7844 | K24: ( ) -
A25: 86149 | B25: PETRA RAMIREZ USCANGA | C25: ACTIVO | D25: ORO | E25: 52000 | F25: 30068.168 | G25: 36942.28 | H25: 1627 | I25: 0 | J25: (924) 152-6974 | K25: ( ) -
A26: 86166 | B26: GABRIELA SANCHEZ GONZALEZ | C26: ACTIVO | D26: PLATA | E26: 60000 | F26: 52572.433 | G26: 13129.87 | H26: 491 | I26: 0 | J26: (924) 127-5593 | K26: ( ) -
A27: 86237 | B27: HERLINDA LOPEZ NO | C27: ACTIVO | D27: ORO | E27: 78600 | F27: 54502.105 | G27: 45312 | H27: 886 | I27: 0 | J27: (924) 110-1679 | K27: ( ) -
A28: 104106 | B28: GERONIMO FRANCO DORA ALICIA | C28: ACTIVO | D28: DIAMANTE | E28: 147000 | F28: 76674.95 | G28: 143505.64 | H28: 237 | I28: 0 | J28: 8331060482
A29: 106746 | B29: YAÑEZ MARTINEZ , MARIA LOURDES | C29: ACTIVO | D29: PLATA | E29: 50000 | F29: 47500.17 | G29: 4134 | H29: 959 | I29: 0 | J29: 8334121349
A30: 107732 | B30: VIGIL IBARRA , EUNICE | C30: ACTIVO | D30: PLATINO | E30: 113000 | F30: 26714.454 | G30: 167821.6 | H30: 1931 | I30: 0 | J30: 8335143760
A31: 108264 | B31: DE LA ROSA SANCHEZ , MA ESTHER | C31: ACTIVO | D31: PLATA | E31: 30000 | F31: 18700.787 | G31: 25943.25 | H31: 2056 | I31: 0 | J31: 8333771045
A32: 110263 | B32: CAMPOZANO FLORES , ELENA | C32: ACTIVO | D32: ORO | E32: 70000 | F32: 43915.903 | G32: 43906 | H32: 986 | I32: 0 | J32: 8334279329
A33: 113504 | B33: SOBREVILLA PEREZ , AURORA | C33: ACTIVO | D33: ORO | E33: 70000 | F33: 54201.638 | G33: 23440 | H33: 1113 | I33: 0 | J33: 8333419217
A34: 115703 | B34: ANDONEY SANTIAGO , TERESA | C34: ACTIVO | D34: PLATA | E34: 50000 | F34: 41001.123 | G34: 16440 | H34: 1326 | I34: 0 | J34: 8333408365
A35: 57064 | B35: MARIA CONCEPCION LOREDO AVALOS | C35: ACTIVO | D35: DIAMANTE VIP | E35: 155000 | F35: 125202.85 | G35: 72384.33 | H35: 95 | I35: 0 | J35: (833) 128-7549 | K35: ( ) -
A36: 57088 | B36: MARIA VICTORIA GARCIA SOLIS | C36: ACTIVO | D36: ORO | E36: 75000 | F36: 72750.803 | G36: 3511.89 | H36: 346 | I36: 0 | J36: (833) 436-4867 | K36: ( ) -
A37: 57163 | B37: VILLALOBOS ARIAS , AMANDA | C37: ACTIVO | D37: PLATA | E37: 50000 | F37: 27752.382 | G37: 44550 | H37: 1488 | I37: 0 | J37: 8333881621
A38: 57212 | B38: EDUVIGES RODRIGUEZ PONCE | C38: ACTIVO | D38: PLATINO | E38: 95000 | F38: 65702.345 | G38: 48707 | H38: 637 | I38: 0 | J38: (833) 204-0294 | K38: ( ) -
A39: 57216 | B39: MARIA GUADALUPE AQUINO BANDA | C39: ACTIVO | D39: DIAMANTE | E39: 139000 | F39: 138000.04 | G39: 2065 | H39: 31 | I39: 0 | J39: (833) 182-1626 | K39: ( ) -
A40: 57225 | B40: MARTHA PATRICIA LOZANO RIVAS | C40: ACTIVO | D40: PLATA | E40: 50000 | F40: 41394.411 | G40: 15461.02 | H40: 1337 | I40: 0 | J40: (833) 534-6271 | K40: (833) 362-6234
A41: 57243 | B41: CLARABELLA HERNANDEZ ALONSO | C41: ACTIVO | D41: ORO | E41: 68000 | F41: 60917.718 | G41: 11751.06 | H41: 513 | I41: 0 | J41: 8333223438 | K41: ( ) -
A42: 57276 | B42: MARTHA PECERO HERNANDEZ | C42: ACTIVO | D42: PLATA | E42: 45000 | F42: 28144.325 | G42: 36171 | H42: 1826 | I42: 0 | J42: 8336955535 | K42: ( ) -
A43: 57290 | B43: NORMA ELIZABETH SALAS MAR | C43: ACTIVO | D43: PLATINO | E43: 103000 | F43: 64701.859 | G43: 62842 | H43: 512 | I43: 0 | J43: (833) 339-1534 | K43: ( ) -
A44: 57299 | B44: VICTORIA LARA ZARAGOZA | C44: ACTIVO | D44: PLATINO | E44: 90000 | F44: 49069.779 | G44: 75809.625 | H44: 1079 | I44: 0 | J44: (833) 284-4530 | K44: ( ) -
A45: 57306 | B45: BERENICE SEGURA DEL ANGEL | C45: ACTIVO | D45: DIAMANTE VIP | E45: 167000 | F45: 122975.89 | G45: 90828 | H45: 137 | I45: 0 | J45: (833) 206-5948 | K45: ( ) -
A46: 57345 | B46: ANA MARISELA SILVA HERNANDEZ | C46: ACTIVO | D46: ORO | E46: 75000 | F46: 51159.401 | G46: 39043 | H46: 1267 | I46: 0 | J46: (833) 239-6089 | K46: ( ) -
A47: 57363 | B47: GUADALUPE FLORES GUZMAN | C47: ACTIVO | D47: PLATINO | E47: 87500 | F47: 86833.917 | G47: 1098.06 | H47: 211 | I47: 0 | J47: (833) 426-1212 | K47: ( ) -
A48: 57371 | B48: REBOLLAR TORRES , NANCY MARGARITA | C48: ACTIVO | D48: PLATA | E48: 50000 | F48: 26663.816 | G48: 42598.34 | H48: 1729 | I48: 0 | J48: 8338447740
A49: 57403 | B49: JOSE LUIS GUZMAN MADRIGALES | C49: ACTIVO | D49: DIAMANTE | E49: 145000 | F49: 111816.1 | G49: 70824.04 | H49: 152 | I49: 0 | J49: (833) 367-4373 | K49: ( ) -
A50: 104785 | B50: GOMEZ GARCIA TOMAS | C50: ACTIVO | D50: PLATINO | E50: 85000 | F50: 66829.864 | G50: 58270.625 | H50: 589 | I50: 0 | J50: 3221372267
A51: 105186 | B51: BELLO SANTIAGO HORTENCIA | C51: ACTIVO | D51: PLATA | E51: 50000 | F51: 46667.027 | G51: 5511.78 | H51: 1009 | I51: 0 | J51: 3222054625
A52: 105401 | B52: ARENAS SANDOVAL ANALLELI GUADALUPE | C52: ACTIVO | D52: PLATA | E52: 50000 | F52: 41104.537 | G52: 14389 | H52: 1426 | I52: 0 | J52: 3231311871
A53: 105647 | B53: TAPIA MARIN KARLA CAROLINA | C53: ACTIVO | D53: DIAMANTE | E53: 130000 | F53: 106585.24 | G53: 46254.25 | H53: 123 | I53: 0 | J53: 3222390874
A54: 105822 | B54: MARQUEZ JACOBO MARITZA | C54: ACTIVO | D54: PLATINO | E54: 98000 | F54: 27952.083 | G54: 125951.8 | H54: 1837 | I54: 0 | J54: 3221163422
A55: 106099 | B55: ESPARZA ALVAREZ DAIRA LIZETTE | C55: ACTIVO | D55: ORO | E55: 62000 | F55: 55571.759 | G55: 10310 | H55: 635 | I55: 0 | J55: 3223267293
A56: 106891 | B56: BLANCO MUÑOZ , EFRAIN | C56: ACTIVO | D56: PLATA | E56: 38000 | F56: 18720.833 | G56: 35816.583 | H56: 2041 | I56: 0 | J56: 3222275257
A57: 106982 | B57: RAMIREZ HERNANDEZ MA. ESTHER | C57: ACTIVO | D57: ORO | E57: 68000 | F57: 62286.568 | G57: 10736.73 | H57: 555 | I57: 0 | J57: 3222700394
A58: 107423 | B58: ROSAS RENDON , FRANCISCO JAVIER | C58: ACTIVO | D58: PLATA | E58: 25000 | F58: 17001.214 | G58: 21079 | H58: 1849 | I58: 0 | J58: 3223694847
A59: 108163 | B59: IBARRA CARO , NADIA LIZBETH | C59: ACTIVO | D59: PLATINO | E59: 101000 | F59: 78635.964 | G59: 63197.987 | H59: 340 | I59: 0 | J59: 3221937145
A60: 110356 | B60: FRANCO CRUZ , NORMA YADIRA | C60: ACTIVO | D60: PLATA | E60: 50000 | F60: 12003.358 | G60: 65661.04 | H60: 1830 | I60: 0 | J60: 3221265052
A61: 112573 | B61: RODRIGUEZ GUZMAN , ANAHI GUADALUPE | C61: ACTIVO | D61: PLATA | E61: 60000 | F61: 59214.383 | G61: 1691 | H61: 487 | I61: 0 | J61: 3221986927
... A65: 116863 | B65: TAGLE VALENTE , DAMARIS YUNUEN | C65: ACTIVO | D65: PLATA | E65: 50000 | F65: 37917.713 | G65: 28421.63 | H65: 1205 | I65: 0 | J65: 3228887818
A66: 32148 | B66: GRACIELA VALENZUELA RODRIGUEZ | C66: ACTIVO | D66: PLATINO | E66: 117500 | F66: 64794.514 | G66: 91480.25 | H66: 316 | I66: 0 | J66: (322)183-5986 | K66: 3221835986
A67: 103594 | B67: PEREZ GONZALEZ BLANCA ESTELA | C67: ACTIVO | D67: DIAMANTE | E67: 135000 | F67: 132857.48 | G67: 3764.75 | H67: 46 | I67: 0 | J67: 9171026400
A68: 103951 | B68: REYES RODRIGUEZ CLARA AURORA | C68: ACTIVO | D68: ORO | E68: 65000 | F68: 45310.694 | G68: 31215.62 | H68: 913 | I68: 0 | J68: 9373780853
A69: 104094 | B69: CORDOVA LEYVA ALICIA | C69: ACTIVO | D69: PLATINO | E69: 84000 | F69: 9712.2876 | G69: 135848.9 | H69: 1978 | I69: 0 | J69: 9371045695
A70: 104517 | B70: HERNANDEZ ALAMILLA SHEILA DEL CARMEN | C70: ACTIVO | D70: PLATA | E70: 50000 | F70: 34614.812 | G70: 34261.87 | H70: 1617 | I70: 0 | J70: 9371269066 | K70: 9371252550
A71: 104683 | B71: ANTONIO CAMARA ANA LILI | C71: ACTIVO | D71: ORO | E71: 55000 | F71: 17330.542 | G71: 64256.8 | H71: 2000 | I71: 0 | J71: 9371547931
A72: 105090 | B72: PEREZ HERNANDEZ ANA AGUSTINA | C72: ACTIVO | D72: ORO | E72: 63000 | F72: 27284.805 | G72: 71233.08 | H72: 1751 | I72: 0 | J72: 9931933989
A73: 105299 | B73: SANCHEZ MORENO BRISEIDA | C73: ACTIVO | D73: PLATINO | E73: 110000 | F73: 32234.511 | G73: 187200.81 | H73: 1626 | I73: 0 | J73: 9171164295
A74: 105314 | B74: FLORES GOMEZ CINDY RUBI | C74: ACTIVO | D74: PLATINO | E74: 120000 | F74: 79924.115 | G74: 82896.8 | H74: 337 | I74: 0 | J74: 9372288931
A75: 105463 | B75: SANTOS HEREDIA ROCIO DEL CARMEN | C75: ACTIVO | D75: ORO | E75: 65000 | F75: 65000 | G75: 3579 | H75: #N/A | I75: 0 | J75: 9934005015
A76: 105585 | B76: DE LA CRUZ ZAMORA LIDIA DEL CARMEN | C76: ACTIVO | D76: ORO | E76: 58000 | F76: 58000 | G76: 518 | H76: 549 | I76: 0 | J76: 9171082272
A77: 105852 | B77: ESLAVA SANDOVAL PETRA | C77: ACTIVO | D77: ORO | E77: 64000 | F77: 10996.632 | G77: 100935.03 | H77: 2124 | I77: 0 | J77: 9171424475
A78: 106130 | B78: PINEDA PALMA FABIOLA | C78: ACTIVO | D78: PLATA | E78: 50000 | F78: 46800.522 | G78: 4943.57 | H78: 1037 | I78: 0 | J78: 9171098714
A79: 106215 | B79: CASTAÑEDA RAMOS LIZBETH | C79: ACTIVO | D79: PLATINO | E79: 91000 | F79: 54585.847 | G79: 70731.84 | H79: 1297 | I79: 0
A80: 106236 | B80: CRUZ MEJIA EDILIA | C80: ACTIVO | D80: ORO | E80: 70000 | F80: 45074.694 | G80: 44359.95 | H80: 1380 | I80: 0 | J80: 9171052992
A81: 106979 | B81: DE LA CRUZ GOMEZ , DOLORES | C81: ACTIVO | D81: DIAMANTE | E81: 136000 | F81: 8365.5367 | G81: 245214.43 | H81: 624 | I81: 0 | J81: 9935146228
A82: 108220 | B82: OLAN GARCIA , YOSHIO | C82: ACTIVO | D82: ORO | E82: 79000 | F82: 69501.439 | G82: 30317.62 | H82: 381 | I82: 0 | J82: 9371170105
A83: 108522 | B83: BUSTAMANTE ESCUDERO , MARIA CRISTI | C83: ACTIVO | D83: PLATA | E83: 30000 | F83: 27113.344 | G83: 4763.16 | H83: 1737 | I83: 0 | J83: 9371404718 | K83: 9371404718
A84: 108635 | B84: DOMINGUEZ HERNANDEZ , GUADALUPE | C84: ACTIVO | D84: ORO | E84: 79000 | F84: 48738.34 | G84: 59500.06 | H84: 941 | I84: 0 | J84: 9371304201 | K84: 9371304201
A85: 108676 | B85: FLOTA GONZALEZ , GLADYS DEL CARMEN | C85: ACTIVO | D85: PLATA | E85: 38000 | F85: 38000 | G85: 9883.63 | H85: 1345 | I85: 0 | J85: 9371412698
A86: 109107 | B86: MONTEJO HERNANDEZ , MARIA ELENA | C86: ACTIVO | D86: PLATA | E86: 50000 | F86: 30801.284 | G86: 41096.35 | H86: 1633 | I86: 0 | J86: 9371675638
A87: 109194 | B87: RINCON OVANDO , DIANA CRISTHELL | C87: ACTIVO | D87: ORO | E87: 69000 | F87: 26747.974 | G87: 84001.31 | H87: 1919 | I87: 0 | J87: 9371105774
A88: 109300 | B88: PINEDA ALEJANDRO , VIVIANA | C88: ACTIVO | D88: PLATA | E88: 60000 | F88: 50667.664 | G88: 14869.73 | H88: 1074 | I88: 0 | J88: 9371511079 | K88: 9371511079
A89: 109448 | B89: DE LA CRUZ SAUZ , CARLOS | C89: ACTIVO | D89: PLATA | E89: 50000 | F89: 40643.557 | G89: 14681.55 | H89: 895 | I89: 0 | J89: 9371182462 | K89: 9371182462
A90: 109569 | B90: BROCA JAVIER , MARIA DEL ROSARIO | C90: ACTIVO | D90: ORO | E90: 70000 | F90: 704.6753 | G90: 141793.17 | H90: 2028 | I90: 0 | J90: 9371279541 | K90: 9371279541
A91: 109597 | B91: FUENTES HERNANDEZ , CAROLINA | C91: ACTIVO | D91: PLATA | E91: 50000 | F91: 50000 | G91: 2192.19 | H91: 847 | I91: 0 | J91: 9371669302 | K91: 9371669302
A92: 109709 | B92: CARRETA SILVAN , CECILIA DEL CARMEN | C92: ACTIVO | D92: ORO | E92: 65000 | F92: 26003.661 | G92: 70695.03 | H92: 1645 | I92: 0 | J92: 3331378047 | K92: 3331378047
A93: 109754 | B93: VARGAS MORALES , EVA INELDA | C93: ACTIVO | D93: ORO | E93: 65000 | F93: 3603.556 | G93: 107962.52 | H93: 2104 | I93: 0 | J93: 9372716994 | K93: 9372716994
A94: 110037 | B94: PEREZ GOMEZ , MARIANA | C94: ACTIVO | D94: PLATA | E94: 40000 | F94: 15502.737 | G94: 40969.92 | H94: 2033 | I94: 0 | J94: 9371625549 | K94: 9371625549
A95: 112110 | B95: ESCALANTE LOPEZ , NIDIA MARIA | C95: ACTIVO | D95: ORO | E95: 65000 | F95: 49789.639 | G95: 24899.67 | H95: 1244 | I95: 0 | J95: 9371342094
A96: 112580 | B96: ARIAS CORDOVA , JUAN ANTONIO | C96: ACTIVO | D96: PLATA | E96: 50000 | F96: 25771.69 | G96: 39989.49 | H96: 1533 | I96: 0 | J96: 9371005540 | K96: 9371005540
A97: 113201 | B97: JIMENEZ GOMEZ , BELEM | C97: ACTIVO | D97: PLATA | E97: 40000 | F97: 39717.581 | G97: 518.01 | H97: 1281 | I97: 0 | J97: 9371717893
A98: 113797 | B98: RAMOS HERNANDEZ , LUCIA | C98: ACTIVO | D98: PLATA | E98: 60000 | F98: 29835.068 | G98: 49801.02 | H98: 1720 | I98: 0 | J98: 9371252077
A99: 114020 | B99: RAMON SANCHEZ , SORAY DEL CARMEN | C99: ACTIVO | D99: PLATA | E99: 60000 | F99: 36669.632 | G99: 45481.58 | H99: 1659 | I99: 0 | J99: 9371714308 | K99: 9371714308
A100: 114290 | B100: DOMINGUEZ TORRUCO , RAUL | C100: ACTIVO | D100: PLATA | E100: 50000 | F100: 840.8807 | G100: 124079.33 | H100: #N/A | I100: 0 | J100: 9371210750
A101: 114893 | B101: MARTINEZ ALPUCHE , YESENIA | C101: ACTIVO | D101: PLATA | E101: 50000 | F101: 25222.142 | G101: 41144.83 | H101: 1835 | I101: 0 | J101: 9371160205 | K101: 9371160205
A102: 115112 | B102: MORALES CORDOVA , OLGA LIDIA | C102: ACTIVO | D102: PLATA | E102: 50000 | F102: 19061.656 | G102: 57771.835 | H102: 2007 | I102: 0 | J102: 9987601423 | K102: 9987601423
A103: 116399 | B103: REYES DE LA CRUZ , ISABEL | C103: ACTIVO | D103: PLATA | E103: 50000 | F103: 41734.02 | G103: 14718.81 | H103: 1274 | I103: 0 | J103: 9371686194 | K103: 9371686194
...

Sheet Hoja4
A1: Llamada efectiva (contestó) | C1: 1 | E1: NO
A2: No contestó | C2: 2 | E2: SI
A3: Buzón | C3: 3
A4: Número incorrecto | C4: 4
A5: Teléfono fuera de servicio | C5: 5
A6: Reagendar llamada
A7: Se negó a contestar
A8: Número cambiado
A9: Otro
